[{"id":"6077724041","site":"Chess.com","date":"2020.12.28","white":"tarlar","black":"SenseiDanya","result":"0-1","currentposition":"2r3k1/4b1p1/3p4/4p3/1N1Bb1p1/4r2p/PP2Q2P/6RK w - -","eco":"B21","ecourl":"https://www.chess.com/openings/Sicilian-Defense-Smith-Morra-Gambit-Declined-Alapin-Formation","whiteelo":"1647","blackelo":"1512","starttime":"06:17:53","endtime":"06:48:41","link":"https://www.chess.com/game/live/6077724041","moves":"1. e4 c5 2. d4 cxd4 3. c3 Nf6 4. Bd3 dxc3 5. Nxc3 Nc6 6. Nf3 d6 7. Bg5 e6 8. Qe2 Be7 9. O-O O-O 10. Rfd1 Qa5 11. Bd2 Qh5 12. Qf1 b6 13. Nb5 Bb7 14. Be2 Nxe4 15. Nfd4 Qg6 16. Bc3 Nxd4 17. Bxd4 a6 18. Nc7 Rac8 19. Nxa6 Ng5 20. Kh1 Nh3 21. f3 Nf4 22. Nb4 h5 23. Bxb6 h4 24. Be3 Nxe2 25. Qxe2 h3 26. Rg1 Qh5 27. g4 Qh7 28. Rg3 f5 29. Bd4 e5 30. Rag1 fxg4 31. Qb5 Qe4 32. Qd3 Qxf3+ 33. Rxf3 Rxf3 34. Qb5 Be4 35. Qe2 Re3+"},{"id":"6070532448","site":"Chess.com","date":"2020.12.27","white":"MidnightRhino","black":"SenseiDanya","result":"0-1","currentposition":"r1b2rk1/ppp3bp/3p2pB/2nPpp2/2PnP2q/2N2P2/PP1QN1PP/RB2K2R w KQ -","eco":"D70","ecourl":"https://www.chess.com/openings/Kings-Indian-Defense-Alekhine-Anti-Grunfeld-Variation","whiteelo":"1702","blackelo":"1512","starttime":"11:34:12","endtime":"11:39:08","link":"https://www.chess.com/game/live/6070532448","moves":"1. d4 Nf6 2. c4 g6 3. f3 Bg7 4. e4 d6 5. Nc3 O-O 6. Bd3 Nc6 7. Nge2 Nd7 8. Be3 e5 9. d5 Nd4 10. Qd2 Nc5 11. Bb1 f5 12. Bh6 Qh4+"},{"id":"6070306082","site":"Chess.com","date":"2020.12.27","white":"Jiggahertz","black":"SenseiDanya","result":"0-1","currentposition":"r2qk2r/p4ppp/2p1p3/2b1Pb2/Qn1N1P2/N7/PP1P2PP/R1B2RK1 w kq -","eco":"B21","ecourl":"https://www.chess.com/openings/Sicilian-Defense-McDonnell-Attack-2...d5-3.e5","whiteelo":"1344","blackelo":"1512","starttime":"10:53:07","endtime":"11:02:36","link":"https://www.chess.com/game/live/6070306082","moves":"1. e4 c5 2. f4 d5 3. e5 Nc6 4. Nf3 Bf5 5. c3 d4 6. Bb5 e6 7. Na3 Ne7 8. O-O Nd5 9. cxd4 cxd4 10. Nxd4 Bc5 11. Bxc6+ bxc6 12. Qa4 Nb4"},{"id":"6070107913","site":"Chess.com","date":"2020.12.27","white":"SenseiDanya","black":"JubsterRexon","result":"1-0","currentposition":"2rnr3/1p2bkpp/pR3pn1/3p4/1P1P4/PB3N2/1B1Q1PPP/4R1K1 b - -","eco":"C02","ecourl":"https://www.chess.com/openings/French-Defense-Advance-Paulsen-Main-Line","whiteelo":"1466","blackelo":"1560","starttime":"10:15:15","endtime":"10:28:36","link":"https://www.chess.com/game/live/6070107913","moves":"1. e4 e6 2. d4 d5 3. e5 c5 4. c3 Nc6 5. Nf3 Qb6 6. a3 f6 7. b4 cxd4 8. cxd4 a6 9. Bd3 Bd7 10. O-O Nge7 11. Nc3 Ng6 12. Re1 Be7 13. Bb2 Nf4 14. Bc2 Rc8 15. Qd2 Ng6 16. Nxd5 exd5 17. e6 Bxe6 18. Rxe6 Kf7 19. Rae1 Rhe8 20. Bb3 Nd8 21. Rxb6"},{"id":"6069962514","site":"Chess.com","date":"2020.12.27","white":"rad_cliff","black":"SenseiDanya","result":"0-1","currentposition":"r4rk1/pQ3ppp/2p5/8/P1b1n3/8/4RPPP/q4NK1 w - -","eco":"C51","ecourl":"https://www.chess.com/openings/Giuoco-Piano-Game-Evans-Accepted-Anderssen-Variation-Cordel-Line","whiteelo":"1294","blackelo":"1466","starttime":"09:46:32","endtime":"09:56:45","link":"https://www.chess.com/game/live/6069962514","moves":"1. e4 e5 2. Nf3 Nc6 3. Bc4 Bc5 4. b4 Bxb4 5. c3 Be7 6. d4 Na5 7. Nxe5 Nxc4 8. Nxc4 d5 9. exd5 Qxd5 10. Ne3 Qd8 11. O-O Nf6 12. Re1 O-O 13. c4 c6 14. a4 Be6 15. Nc3 Bb4 16. Bd2 Qxd4 17. Qb3 Qxd2 18. Qxb4 Ne4 19. Re2 Qxc3 20. Qxb7 Qxa1+ 21. Nf1 Bxc4"},{"id":"6069689253","site":"Chess.com","date":"2020.12.27","white":"SenseiDanya","black":"AlexSem","result":"1-0","currentposition":"r2kqR2/4Q2p/p5p1/1p1Np3/4p3/4B3/PPP3PP/R5K1 b - -","eco":"C70","ecourl":"https://www.chess.com/openings/Ruy-Lopez-Opening-Morphy-Defense-Caro-Variation-5.Bb3","whiteelo":"1412","blackelo":"1469","starttime":"08:48:29","endtime":"08:59:00","link":"https://www.chess.com/game/live/6069689253","moves":"1. e4 e5 2. Nf3 Nc6 3. Bb5 a6 4. Ba4 b5 5. Bb3 Nf6 6. d4 d6 7. Ng5 Bg4 8. Bxf7+ Ke7 9. f3 Bh5 10. Bxh5 Nxh5 11. d5 Nb8 12. Ne6 Qd7 13. O-O c6 14. f4 cxd5 15. Nxf8 Rxf8 16. Qxh5 Nc6 17. Nc3 dxe4 18. Nd5+ Kd8 19. Be3 g6 20. Qg5+ Ne7 21. fxe5 dxe5 22. Rxf8+ Qe8 23. Qxe7+"},{"id":"6069536239","site":"Chess.com","date":"2020.12.27","white":"SenseiDanya","black":"AdityaRajagopal","result":"1-0","currentposition":"r2qr2k/1p5Q/p1n5/3p1nN1/PP1P4/2P4P/5PPB/R3R1K1 b - -","eco":"B13","ecourl":"https://www.chess.com/openings/Caro-Kann-Defense-Exchange-Variation...4.Bd3-Nc6-5.c3-g6","whiteelo":"1412","blackelo":"1176","starttime":"08:13:29","endtime":"08:23:41","link":"https://www.chess.com/game/live/6069536239","moves":"1. e4 c6 2. d4 d5 3. exd5 cxd5 4. Bd3 Nc6 5. c3 g6 6. h3 Bg7 7. Nf3 e6 8. O-O Nge7 9. Bf4 O-O 10. Nbd2 f6 11. Re1 Re8 12. b4 a6 13. a4 g5 14. Bh2 h5 15. Nxg5 e5 16. Qxh5 e4 17. Ndxe4 Bf5 18. Nxf6+ Bxf6 19. Qf7+ Kh8 20. Qxf6+ Kg8 21. Qf7+ Kh8 22. Bxf5 Nxf5 23. Qh7#"},{"id":"6069461723","site":"Chess.com","date":"2020.12.27","white":"Prashanthsrn","black":"SenseiDanya","result":"0-1","currentposition":"r4rk1/p4pb1/1p5p/2pp4/8/5N2/PP2KPPP/1b6 w - -","eco":"B30","ecourl":"https://www.chess.com/openings/Sicilian-Defense-Old-Sicilian-Variation","whiteelo":"1317","blackelo":"1360","starttime":"07:55:52","endtime":"08:05:29","link":"https://www.chess.com/game/live/6069461723","moves":"1. e4 c5 2. Nf3 Nc6 3. Bc4 e6 4. Nc3 Nf6 5. e5 d5 6. exf6 dxc4 7. fxg7 Bxg7 8. Ne4 b6 9. d3 cxd3 10. cxd3 Bb7 11. Bf4 O-O 12. Nfg5 Nb4 13. O-O h6 14. Nf3 Nxd3 15. Rb1 Bxe4 16. Qe2 Qd5 17. Rfd1 Nxf4 18. Rxd5 Nxe2+ 19. Kf1 exd5 20. Kxe2 Bxb1"},{"id":"6059011255","site":"Chess.com","date":"2020.12.25","white":"SenseiDanya","black":"Gainztrain13","result":"1-0","currentposition":"2Q1k2r/4bqpp/8/2pp4/2p2B2/2P3P1/PP3P1P/R3R1K1 b kq -","eco":"B22","ecourl":"https://www.chess.com/openings/Sicilian-Defense-Alapin-Variation-Barmen-Defense-4.d4-Nc6-5.Nf3","whiteelo":"1188","blackelo":"1093","starttime":"23:51:13","endtime":"23:58:56","link":"https://www.chess.com/game/live/6059011255","moves":"1. e4 c5 2. c3 d5 3. exd5 Qxd5 4. d4 Nc6 5. Nf3 Nf6 6. Na3 a6 7. Nc4 Nd7 8. Ne3 Qd6 9. d5 Nce5 10. Be2 Nxf3+ 11. Bxf3 e6 12. Nc4 Qc7 13. dxe6 fxe6 14. O-O Nf6 15. g3 b5 16. Bxa8 bxc4 17. Bf4 Qf7 18. Qa4+ Bd7 19. Qxa6 Nd5 20. Bxd5 exd5 21. Rfe1+ Be7 22. Qa8+ Bc8 23. Qxc8#"},{"id":"6058820812","site":"Chess.com","date":"2020.12.25","white":"SenseiDanya","black":"sadaman","result":"1-0","currentposition":"1R4kb/3r1p1p/p2p2pB/2q5/2B2Q2/5N1P/5PK1/4R3 b - -","eco":"B22","ecourl":"https://www.chess.com/openings/Sicilian-Defense-Alapin-Variation-2...Nc6-3.d4","whiteelo":"923","blackelo":"1568","starttime":"23:17:54","endtime":"23:32:36","link":"https://www.chess.com/game/live/6058820812","moves":"1. e4 c5 2. c3 Nc6 3. d4 d6 4. Nf3 Nf6 5. h3 a6 6. Bd3 g6 7. O-O Bg7 8. Be3 cxd4 9. cxd4 O-O 10. Nc3 Be6 11. d5 Bxh3 12. dxc6 bxc6 13. gxh3 Qd7 14. Kg2 c5 15. Qd2 Rfd8 16. Bh6 Bh8 17. Nd5 Nxd5 18. exd5 Rab8 19. Rab1 e6 20. dxe6 Qxe6 21. Rfe1 Qxa2 22. Qf4 Rd7 23. Bc4 Qa5 24. b4 Qc7 25. bxc5 Qxc5 26. Rxb8+"},{"id":"6058642436","site":"Chess.com","date":"2020.12.25","white":"SenseiDanya","black":"HumanFtw","result":"1-0","currentposition":"r7/1b6/p3k1p1/2pN3p/1p2P2B/1P6/1PP3P1/2KR1R2 w - c6","eco":"B00","ecourl":"https://www.chess.com/openings/Kings-Pawn-Opening-Owens-Defense-2.d4-Bb7","whiteelo":"923","blackelo":"1361","starttime":"22:48:53","endtime":"23:00:38","link":"https://www.chess.com/game/live/6058642436","moves":"1. e4 b6 2. d4 Bb7 3. Nc3 g6 4. Be3 Bg7 5. Qd2 h6 6. O-O-O e6 7. h4 d6 8. f4 e5 9. dxe5 Ne7 10. h5 Nbc6 11. hxg6 fxg6 12. Nf3 a6 13. Bc4 dxe5 14. Qf2 Qc8 15. fxe5 Qg4 16. Nh2 Rf8 17. Nxg4 Rxf2 18. Bxf2 h5 19. Nf6+ Bxf6 20. exf6 b5 21. Bb3 Na5 22. fxe7 Nxb3+ 23. axb3 Kxe7 24. Rhf1 b4 25. Bh4+ Ke6 26. Nd5 c5"},{"id":"6058538889","site":"Chess.com","date":"2020.12.25","white":"ChessAwesomeness21","black":"SenseiDanya","result":"0-1","currentposition":"r1b2rk1/ppp2ppp/3p4/8/1P1bP3/P2B4/2P1NnP1/R3QRKq w - -","eco":"C42","ecourl":"https://www.chess.com/openings/Petrovs-Defense-Three-Knights-Game","whiteelo":"882","blackelo":"923","starttime":"22:32:47","endtime":"22:42:14","link":"https://www.chess.com/game/live/6058538889","moves":"1. e4 e5 2. Nc3 Nf6 3. Nf3 Nc6 4. d4 exd4 5. Nxd4 Bb4 6. Bd2 Nxd4 7. a3 Ba5 8. Bd3 d6 9. O-O O-O 10. b4 Bb6 11. Be3 Ng4 12. Bxd4 Bxd4 13. Ne2 Qh4 14. h3 Nxf2 15. Qe1 Nxh3+ 16. Kh1 Nf2+ 17. Kg1 Qh1#"},{"id":"6053664646","site":"Chess.com","date":"2020.12.25","white":"Pushdapawn","black":"SenseiDanya","result":"0-1","currentposition":"6rk/p4prp/1p2p2b/3pPp1q/8/2P2P2/PP2RQPB/3R3K w - -","eco":"D00","ecourl":"https://www.chess.com/openings/Queens-Pawn-Opening-Accelerated-London-Steinitz-Countergambit","whiteelo":"2326","blackelo":"2321","starttime":"09:38:28","endtime":"09:48:28","link":"https://www.chess.com/game/live/6053664646","moves":"1. d4 d5 2. Bf4 c5 3. e3 cxd4 4. exd4 Nc6 5. c3 Nf6 6. Nf3 g6 7. h3 Bg7 8. Bd3 O-O 9. O-O Bf5 10. Bxf5 gxf5 11. Qb3 b6 12. Nbd2 e6 13. Ne5 Nxe5 14. dxe5 Ne4 15. Nf3 Kh8 16. Rad1 Rc8 17. Nd4 Qh4 18. Bh2 Rg8 19. f3 Ng3 20. Rfe1 Bh6 21. Qc2 Rg7 22. Qf2 Rcg8 23. Ne2 Nxe2+ 24. Rxe2 Qxh3 25. Kh1 Qh5"},{"id":"6053571257","site":"Chess.com","date":"2020.12.25","white":"KarateBaby","black":"SenseiDanya","result":"1/2-1/2","currentposition":"8/8/8/6rk/8/4K2b/8/8 b - -","eco":"A01","ecourl":"https://www.chess.com/openings/Nimzowitsch-Larsen-Attack-English-Variation","whiteelo":"2190","blackelo":"2312","starttime":"09:17:10","endtime":"09:27:44","link":"https://www.chess.com/game/live/6053571257","moves":"1. b3 c5 2. Bb2 Nc6 3. e3 Nf6 4. Nf3 d5 5. Bb5 Bd7 6. O-O e6 7. d3 Bd6 8. Bxc6 Bxc6 9. Ne5 Nd7 10. f4 Bxe5 11. fxe5 Qg5 12. d4 Qxe3+ 13. Kh1 cxd4 14. Bxd4 Qg5 15. Qe2 O-O 16. Nc3 Rac8 17. Rf3 Qe7 18. Raf1 b6 19. Rh3 f6 20. exf6 Nxf6 21. Re3 Ne4 22. Nxe4 dxe4 23. Re1 Rf5 24. Rg3 e5 25. Be3 Qe6 26. Qa6 Rc7 27. Rd1 h6 28. h3 Rcf7 29. a4 Kh7 30. a5 b5 31. Kh2 R5f6 32. Rd8 Rf1 33. Qc8 Qxc8 34. Rxc8 R1f6 35. Bc5 e3 36. Bxe3 Be4 37. Rc5 Re6 38. Rxb5 Bxc2 39. b4 Be4 40. Rc5 a6 41. b5 axb5 42. Rxb5 Rfe7 43. Rb6 Rxb6 44. Bxb6 Bb7 45. Re3 Kg6 46. Kg3 Kf5 47. Rc3 Re6 48. Rc7 Rg6+ 49. Kf2 Rxg2+ 50. Kf1 Bd5 51. Rc5 Be4 52. Bc7 Kf4 53. Bxe5+ Kf5 54. Bxg7+ Kg6 55. Bxh6 Kxh6 56. Re5 Bf3 57. Re6+ Kh5 58. a6 Ra2 59. Rf6 Bg2+ 60. Kg1 Bxh3 61. Rb6 Kg4 62. Rb4+ Kg3 63. Rb3+ Kh4 64. a7 Rxa7 65. Rb4+ Bg4 66. Rb3 Rf7 67. Rb2 Rf6 68. Rh2+ Kg5 69. Rb2 Rg6 70. Rb5+ Bf5 71. Rb2 Kf4+ 72. Kf2 Rf6 73. Rb4+ Kg5 74. Kg3 Bg4 75. Rb5+ Bf5 76. Rb4 Rg6 77. Rf4 Kh5+ 78. Kf2 Rg4 79. Rf3 Rg5 80. Rh3+ Bxh3 81. Ke3"},{"id":"6053447138","site":"Chess.com","date":"2020.12.25","white":"gilepile70","black":"SenseiDanya","result":"0-1","currentposition":"8/6k1/4R1p1/1p1K1p2/7r/8/6P1/4N3 w - -","eco":"B31","ecourl":"https://www.chess.com/openings/Sicilian-Defense-Nyezhmetdinov-Rossolimo-Fianchetto-Variation-4.O-O-Bg7-5.Re1-e5-6.c3","whiteelo":"2311","blackelo":"2315","starttime":"08:48:33","endtime":"08:58:22","link":"https://www.chess.com/game/live/6053447138","moves":"1. e4 c5 2. Nf3 Nc6 3. Bb5 g6 4. O-O Bg7 5. Re1 e5 6. c3 Nge7 7. d4 cxd4 8. cxd4 exd4 9. e5 O-O 10. Bf4 Qb6 11. Na3 a6 12. Bd3 Qa7 13. Nc4 b5 14. Nd6 Bb7 15. Qd2 Nc8 16. Nxb7 Qxb7 17. Bh6 Nb6 18. Qf4 Nd5 19. Qh4 f6 20. Be4 Nxe5 21. Bxg7 Kxg7 22. Rad1 Rae8 23. Nxd4 Kh8 24. f4 f5 25. Bxd5 Qxd5 26. fxe5 Rxe5 27. Rxe5 Qxe5 28. Nf3 Qg7 29. Qd4 Qxd4+ 30. Rxd4 Rc8 31. Rxd7 Rc1+ 32. Kf2 Rc2+ 33. Rd2 Rc5 34. h4 Kg7 35. Rd7+ Kf6 36. Rd6+ Ke7 37. Rxa6 Rc2+ 38. Kg3 Rxb2 39. Ra7+ Kf6 40. Rxh7 Rxa2 41. Rb7 Rb2 42. Ng5 Ke5 43. Re7+ Kf6 44. Re6+ Kg7 45. Nf3 Rb3 46. Kf4 Rb4+ 47. Ke5 Re4+ 48. Kd5 Rg4 49. Ne1 Rxh4"},{"id":"6053359325","site":"Chess.com","date":"2020.12.25","white":"SenseiDanya","black":"chesskid1220","result":"1-0","currentposition":"2r2qk1/ppN3p1/2n1R1Pr/5p1p/3P1Q1P/5P2/PPP5/2K1R3 b - -","eco":"D00","ecourl":"https://www.chess.com/openings/Queens-Pawn-Opening-Accelerated-London-Steinitz-Countergambit","whiteelo":"2307","blackelo":"2290","starttime":"08:27:23","endtime":"08:36:32","link":"https://www.chess.com/game/live/6053359325","moves":"1. d4 d5 2. Bf4 c5 3. e3 Nc6 4. Nc3 cxd4 5. exd4 Bf5 6. Nf3 e6 7. Ne5 Nf6 8. g4 Be4 9. f3 Bg6 10. h4 h5 11. Nxg6 fxg6 12. Bd3 Kf7 13. g5 Ng8 14. Qd2 Bd6 15. O-O-O Nge7 16. Rhe1 Nf5 17. Bxf5 gxf5 18. g6+ Kg8 19. Rxe6 Bxf4 20. Qxf4 Rh6 21. Rde1 Qf8 22. Nxd5 Rc8 23. Nc7"},{"id":"6045410873","site":"Chess.com","date":"2020.12.24","white":"Matthilde","black":"SenseiDanya","result":"0-1","currentposition":"8/2R2r2/6kp/4Bp2/3P4/1n2K2P/5PP1/8 w - -","eco":"B31","ecourl":"https://www.chess.com/openings/Sicilian-Defense-Nyezhmetdinov-Rossolimo-Fianchetto-Variation-4.Bxc6-dxc6-5.d3-Bg7-6.h3","whiteelo":"2292","blackelo":"2299","starttime":"08:28:22","endtime":"08:38:36","link":"https://www.chess.com/game/live/6045410873","moves":"1. e4 c5 2. Nf3 Nc6 3. Bb5 g6 4. Bxc6 dxc6 5. d3 Bg7 6. h3 e5 7. Be3 b6 8. a4 a5 9. Nbd2 Ne7 10. Nc4 Qc7 11. O-O O-O 12. b4 axb4 13. a5 bxa5 14. Bxc5 Be6 15. Nb6 Ra6 16. Na4 Rd8 17. Re1 h6 18. Qc1 Kh7 19. Be3 Qc8 20. Nc5 Ra8 21. Nxe6 Qxe6 22. Bb6 Rdb8 23. Rxa5 Rxa5 24. Bxa5 c5 25. Nd2 Qa6 26. Nc4 Nc6 27. Bc7 Rc8 28. Bd6 Qb5 29. Qb2 Ra8 30. c3 Ra4 31. Rb1 Qa6 32. Bxc5 Ra2 33. Qb3 bxc3 34. Qxc3 Qa4 35. Qb3 Qxb3 36. Rxb3 Nd8 37. Bd6 f6 38. Ne3 Ne6 39. Nd5 Ra7 40. Be7 f5 41. Rb6 Nd4 42. Nf6+ Bxf6 43. Bxf6 Rd7 44. Bxe5 Ne2+ 45. Kf1 Nc1 46. exf5 gxf5 47. d4 Nd3 48. Ke2 Nc1+ 49. Ke3 Rf7 50. Rc6 Nb3 51. Rc7 Kg6"},{"id":"6045331111","site":"Chess.com","date":"2020.12.24","white":"SenseiDanya","black":"Matthilde","result":"1-0","currentposition":"r1bk3r/ppq3pp/2nb2n1/2p2pN1/2Bp1P2/3P2Q1/PPPBN1PP/2KRR3 b - -","eco":"B10","ecourl":"https://www.chess.com/openings/Caro-Kann-Defense-Goldman-Variation","whiteelo":"2291","blackelo":"2309","starttime":"08:09:41","endtime":"08:13:33","link":"https://www.chess.com/game/live/6045331111","moves":"1. e4 c6 2. Nc3 d5 3. Qf3 d4 4. Bc4 e6 5. Nce2 c5 6. d3 Nc6 7. Qg3 Nge7 8. Bd2 Ng6 9. f4 f5 10. exf5 exf5 11. O-O-O Bd6 12. Nf3 Qc7 13. Rhe1 Kd8 14. Ng5"},{"id":"6045287511","site":"Chess.com","date":"2020.12.24","white":"uwinthant","black":"SenseiDanya","result":"0-1","currentposition":"r1b1r1k1/pp3p1p/6p1/2Pp4/3b4/4qPP1/PP2B1KP/R2QR3 w - -","eco":"E60","ecourl":"https://www.chess.com/openings/Kings-Indian-Defense-3.Nf3","whiteelo":"2246","blackelo":"2282","starttime":"07:59:26","endtime":"08:03:24","link":"https://www.chess.com/game/live/6045287511","moves":"1. d4 Nf6 2. Nf3 g6 3. c4 Bg7 4. Nc3 O-O 5. e4 d6 6. Be2 e5 7. Be3 exd4 8. Nxd4 Re8 9. f3 c6 10. Bf2 d5 11. exd5 cxd5 12. c5 Nc6 13. O-O Nh5 14. Ncb5 Nf4 15. Re1 Qg5 16. g3 Nh3+ 17. Kg2 Nxf2 18. Kxf2 Nxd4 19. Nxd4 Qe3+ 20. Kg2 Bxd4"},{"id":"6045175321","site":"Chess.com","date":"2020.12.24","white":"SenseiDanya","black":"Witpensstekelstert","result":"1-0","currentposition":"8/6p1/1r4k1/7p/8/1r6/R7/5K2 b - -","eco":"D20","ecourl":"https://www.chess.com/openings/Queens-Gambit-Accepted-Central-Variation-McDonnell-Defense-4.Nf3-Bb4","whiteelo":"2275","blackelo":"2290","starttime":"07:32:57","endtime":"07:43:20","link":"https://www.chess.com/game/live/6045175321","moves":"1. d4 d5 2. c4 dxc4 3. e4 e5 4. Nf3 Bb4+ 5. Bd2 Bxd2+ 6. Nbxd2 exd4 7. Bxc4 Nc6 8. O-O Be6 9. Bxe6 fxe6 10. Qb3 Qd7 11. Qxb7 Rb8 12. Qa6 Nf6 13. Rac1 Rb6 14. Qa3 Rf8 15. Rc5 Ng4 16. h3 Nf6 17. Rfc1 a6 18. Qa4 Ne5 19. Qxd7+ Nfxd7 20. Nxe5 Nxc5 21. Rxc5 Rxb2 22. Ndf3 Rxa2 23. Rxc7 Rf4 24. Nc6 Rxe4 25. Nfxd4 Kf8 26. Re7 Rxd4 27. Rxe6 Rd1+ 28. Kh2 Rxf2 29. Re4 Rdd2 30. Rg4 h5 31. Rg5 Kf7 32. Kg1 Kf6 33. h4 Rf5 34. Rg3 Rf4 35. Ra3 Rd1+ 36. Kh2 Rxh4+ 37. Kg3 Rg4+ 38. Kf2 Rd2+ 39. Kf3 Rgxg2 40. Rxa6 Rgf2+ 41. Ke3 Rfe2+ 42. Kf3 Re6 43. Rb6 Rc2 44. Rb4 Rcxc6 45. Rf4+ Kg5 46. Ra4 Rf6+ 47. Ke3 Rfe6+ 48. Kf3 Rc3+ 49. Kf2 Rb6 50. Ra2 Rcb3 51. Ra5+ Kg6 52. Ra7 Rc6 53. Ra2 Rcb6 54. Kf1"},{"id":"6037079635","site":"Chess.com","date":"2020.12.23","white":"SenseiDanya","black":"EdawgChessMood","result":"1-0","currentposition":"4qr2/r1p2kQ1/2R2B2/p2p1B1p/1p1P4/3P2P1/PP6/1K6 b - -","eco":"B06","ecourl":"https://www.chess.com/openings/Modern-Defense-Standard-Line-3...d6","whiteelo":"2266","blackelo":"1859","starttime":"08:17:59","endtime":"08:27:57","link":"https://www.chess.com/game/live/6037079635","moves":"1. e4 g6 2. d4 Bg7 3. Nc3 d6 4. Be3 a6 5. h4 h5 6. Qd2 b5 7. f3 Bb7 8. Nh3 Nd7 9. Ng5 e6 10. g3 Ne7 11. Bh3 b4 12. Ne2 a5 13. Nf4 Nf8 14. O-O-O Bh6 15. Kb1 Bxg5 16. hxg5 Nh7 17. Nd3 Ba6 18. f4 Bxd3 19. cxd3 Qb8 20. Rc1 d5 21. Rhf1 Kd7 22. f5 gxf5 23. exf5 exf5 24. Rxf5 Nxf5 25. Bxf5+ Ke7 26. Bf4 Ra7 27. Be5 f6 28. gxf6+ Nxf6 29. Qg5 Rf8 30. Rc6 Qe8 31. Bxf6+ Kf7 32. Qg7#"},{"id":"6036963373","site":"Chess.com","date":"2020.12.23","white":"SenseiDanya","black":"dm85","result":"1-0","currentposition":"4b1k1/6R1/4N1B1/b3p3/4P2P/6P1/2P1KP2/8 b - -","eco":"D00","ecourl":"https://www.chess.com/openings/Queens-Pawn-Opening-Chigorin-Variation-2...Nf6","whiteelo":"2265","blackelo":"2256","starttime":"07:50:32","endtime":"08:00:50","link":"https://www.chess.com/game/live/6036963373","moves":"1. d4 Nf6 2. Nc3 d5 3. Bf4 c5 4. e3 Nc6 5. Nb5 e5 6. dxe5 a6 7. Nc3 d4 8. exf6 dxc3 9. Qxd8+ Kxd8 10. O-O-O+ Ke8 11. bxc3 gxf6 12. Bc4 Be6 13. Bd5 Rg8 14. g3 Rd8 15. c4 Nb4 16. e4 Nxa2+ 17. Kb2 Nb4 18. Ne2 Nc6 19. Rd3 Ne5 20. Bxe5 fxe5 21. Rhd1 Be7 22. Nc3 Rg6 23. h4 Rd6 24. Kc1 Bg4 25. R1d2 Bc8 26. Na4 Rdf6 27. Rb3 b5 28. cxb5 axb5 29. Rxb5 Bd7 30. Rb8+ Bd8 31. Nxc5 Rd6 32. Rb7 Bc6 33. Bxf7+ Kf8 34. Bxg6 Rxd2 35. Ne6+ Kg8 36. Rg7+ Kh8 37. Rxh7+ Kg8 38. Kxd2 Ba5+ 39. Ke2 Be8 40. Rg7+"},{"id":"6036860881","site":"Chess.com","date":"2020.12.23","white":"hbpencil1","black":"SenseiDanya","result":"0-1","currentposition":"3r4/pk3p2/1np1pb2/4q2p/1p6/1N4P1/PPP1QP1P/1K1R4 w - -","eco":"C11","ecourl":"https://www.chess.com/openings/French-Defense-Classical-Burn-Morozevich-Line-7.Nf3-b6","whiteelo":"2089","blackelo":"2257","starttime":"07:26:08","endtime":"07:33:32","link":"https://www.chess.com/game/live/6036860881","moves":"1. e4 e6 2. d4 d5 3. Nc3 Nf6 4. Bg5 dxe4 5. Nxe4 Be7 6. Bxf6 gxf6 7. Nf3 b6 8. Be2 Bb7 9. Nc3 Rg8 10. Rg1 c6 11. Qd2 Nd7 12. O-O-O Qc7 13. Kb1 O-O-O 14. Bd3 f5 15. Qe2 Bf6 16. Ba6 b5 17. Bxb7+ Kxb7 18. g3 Nb6 19. Rge1 b4 20. Ne4 fxe4 21. Qxe4 h5 22. Nd2 Rxd4 23. Qe2 Rgd8 24. Nb3 Rxd1+ 25. Rxd1 Qe5"},{"id":"6036738198","site":"Chess.com","date":"2020.12.23","white":"SenseiDanya","black":"Schwindelaar","result":"1-0","currentposition":"1r5r/1b1Rbk2/p5p1/1p2p2p/4P2P/2B2P2/PPP1B1P1/1K5R b - -","eco":"B06","ecourl":"https://www.chess.com/openings/Modern-Defense-Standard-Line-3...d6","whiteelo":"2252","blackelo":"2300","starttime":"06:56:39","endtime":"07:01:33","link":"https://www.chess.com/game/live/6036738198","moves":"1. e4 g6 2. d4 Bg7 3. Nc3 d6 4. Be3 a6 5. Qd2 b5 6. h4 h5 7. f3 Nd7 8. Nh3 Bb7 9. Ng5 e6 10. O-O-O Qe7 11. Kb1 Rd8 12. Ne2 c5 13. Nf4 cxd4 14. Bxd4 e5 15. Bc3 Nc5 16. Nd5 Qd7 17. Ba5 Rb8 18. Nb6 Qc6 19. Qxd6 Qxd6 20. Rxd6 Bf8 21. Rd1 Be7 22. Be2 Nf6 23. Bc3 Ncd7 24. Nxd7 Nxd7 25. Nxf7 Kxf7 26. Rxd7"},{"id":"6028598670","site":"Chess.com","date":"2020.12.22","white":"VanyaHargreeves","black":"SenseiDanya","result":"0-1","currentposition":"6k1/K5P1/3b4/1q6/8/8/8/8 w - -","eco":"E60","ecourl":"https://www.chess.com/openings/Kings-Indian-Defense-Fianchetto-Variation-4...O-O","whiteelo":"2233","blackelo":"2242","starttime":"08:22:05","endtime":"08:32:38","link":"https://www.chess.com/game/live/6028598670","moves":"1. d4 Nf6 2. c4 g6 3. g3 Bg7 4. Bg2 O-O 5. Nc3 d6 6. Nf3 Nbd7 7. O-O e5 8. e4 c6 9. h3 Qa5 10. Re1 exd4 11. Nxd4 Ne5 12. Bf1 Re8 13. Be3 Be6 14. Nxe6 Rxe6 15. Kg2 Rae8 16. c5 dxc5 17. f4 Ned7 18. e5 Nxe5 19. fxe5 Rxe5 20. Bd2 Rxe1 21. Bxe1 Qc7 22. a4 h5 23. Bf2 b6 24. Qf3 Nd7 25. Bc4 Ne5 26. Qf4 g5 27. Qe4 Qd7 28. Rd1 Qe7 29. Be2 g4 30. hxg4 hxg4 31. Bd3 Nxd3 32. Qxd3 Qf6 33. Rh1 Rd8 34. Qh7+ Kf8 35. Qe4 Rd2 36. Qe3 Qf3+ 37. Qxf3 gxf3+ 38. Kxf3 Rxb2 39. Ne4 Rb3+ 40. Kf4 Rb4 41. g4 Rxa4 42. Rd1 Ke7 43. Bh4+ f6 44. Kf5 Ra3 45. Rf1 c4 46. Nxf6 Kf7 47. Nh5 c3 48. g5 c2 49. g6+ Kg8 50. Bg5 Ra5+ 51. Kg4 Ra4+ 52. Kh3 Ra5 53. Kg4 Rxg5+ 54. Kxg5 Bb2 55. Nf6+ Kf8 56. Ne4+ Kg7 57. Rf7+ Kg8 58. Rf1 c1=Q+ 59. Rxc1 Bxc1+ 60. Kf5 Bb2 61. Nd6 a5 62. Nc8 a4 63. Nxb6 a3 64. Nd7 a2 65. Nb8 a1=Q 66. Nxc6 Qf1+ 67. Ke6 Qc4+ 68. Kd7 Qd5+ 69. Kc8 Be5 70. Kb7 Bd6 71. Ka7 Qxc6 72. g7 Qb5"},{"id":"6017541705","site":"Chess.com","date":"2020.12.20","white":"TheMomBodShuffle","black":"SenseiDanya","result":"0-1","currentposition":"R7/6pk/3p4/4p2p/1P6/3P1K1P/5P2/2q5 w - -","eco":"A28","ecourl":"https://www.chess.com/openings/English-Opening-Four-Knights-Variation","whiteelo":"2325","blackelo":"2234","starttime":"22:55:44","endtime":"23:01:54","link":"https://www.chess.com/game/live/6017541705","moves":"1. c4 e5 2. Nc3 Nf6 3. Nf3 Nc6 4. e4 Bb4 5. Bd3 d6 6. O-O Bg4 7. a3 Bc5 8. Nd5 Nxd5 9. cxd5 Nd4 10. Be2 Nxe2+ 11. Qxe2 O-O 12. h3 Bh5 13. g4 Bg6 14. d3 c6 15. b4 Bb6 16. dxc6 bxc6 17. Qa2 Kh8 18. Qc2 Rc8 19. Be3 Qe7 20. Bxb6 axb6 21. Rfc1 b5 22. a4 bxa4 23. Qxa4 f5 24. exf5 Bxf5 25. gxf5 Rxf5 26. Kg2 Rcf8 27. Qxc6 Rxf3 28. Qxf3 Rxf3 29. Kxf3 h5 30. Ra8+ Kh7 31. Kg3 Qg5+ 32. Kf3 Qxc1"},{"id":"6017411483","site":"Chess.com","date":"2020.12.20","white":"MiguelMejiaE","black":"SenseiDanya","result":"0-1","currentposition":"6k1/4p3/8/1P3Pp1/8/7r/1R5K/5q2 w - -","eco":"B06","ecourl":"https://www.chess.com/openings/Modern-Defense-with-1-e4-2.d4-Bg7-3.Nf3-d6","whiteelo":"2197","blackelo":"2224","starttime":"22:35:09","endtime":"22:45:05","link":"https://www.chess.com/game/live/6017411483","moves":"1. e4 g6 2. d4 Bg7 3. Nf3 d6 4. h3 Nf6 5. Nc3 O-O 6. Bc4 Nxe4 7. Bxf7+ Rxf7 8. Nxe4 h6 9. c3 d5 10. Nc5 Nc6 11. Bf4 Rxf4 12. Qd3 Qd6 13. O-O-O b6 14. Nb3 Bf5 15. Qd2 a5 16. Ne5 Nxe5 17. dxe5 Bxe5 18. Qxd5+ Qxd5 19. Rxd5 Bf6 20. f3 c5 21. Re1 a4 22. Nd2 a3 23. g4 axb2+ 24. Kxb2 Rb4+ 25. Nb3 c4 26. gxf5 cxb3 27. axb3 Rc8 28. Re3 g5 29. Rd7 Rh4 30. Rb7 Rxh3 31. Rxb6 h5 32. b4 h4 33. Kb3 Rh1 34. Ra6 h3 35. Ra2 h2 36. Rb2 Rxc3+ 37. Rxc3 Bxc3 38. Kxc3 Rc1+ 39. Kd2 h1=Q 40. b5 Qd1+ 41. Ke3 Rc3+ 42. Kf2 Rxf3+ 43. Kg2 Qf1+ 44. Kh2 Rh3#"},{"id":"6017287136","site":"Chess.com","date":"2020.12.20","white":"SenseiDanya","black":"CrackrazorATM","result":"1-0","currentposition":"r3k3/2pN2pp/pp6/3B1pNb/P2P1P2/1P5P/2P2P2/R5K1 b - -","eco":"B01","ecourl":"https://www.chess.com/openings/Scandinavian-Defense-Mieses-Kotrc-Gubinsky-Melts-Defense-4.d4-Nf6-5.Nf3","whiteelo":"2216","blackelo":"2233","starttime":"22:16:30","endtime":"22:25:18","link":"https://www.chess.com/game/live/6017287136","moves":"1. e4 d5 2. exd5 Qxd5 3. Nc3 Qd6 4. d4 Nf6 5. Nf3 Nc6 6. h3 a6 7. Bc4 e6 8. O-O Be7 9. Bg5 O-O 10. a4 Rd8 11. Ne2 Qb4 12. b3 Nd5 13. Bxe7 Qxe7 14. Re1 Bd7 15. Ng3 Qf6 16. Ne4 Qh6 17. Nc5 b6 18. Nd3 Nce7 19. Nde5 Be8 20. Bd3 f6 21. Ng4 Qf4 22. Rxe6 f5 23. g3 Nc3 24. gxf4 Nxd1 25. Nge5 Nc3 26. Rxe7 Bh5 27. Ng5 Nd5 28. Bc4 Kf8 29. Rd7 Ke8 30. Bxd5 Rxd7 31. Nxd7"},{"id":"6017053070","site":"Chess.com","date":"2020.12.20","white":"SenseiDanya","black":"fanof163","result":"1-0","currentposition":"7Q/5K2/5B1k/3p4/8/8/5P2/8 b - -","eco":"D00","ecourl":"https://www.chess.com/openings/Queens-Pawn-Opening-Accelerated-London-System","whiteelo":"2207","blackelo":"2211","starttime":"21:42:17","endtime":"21:52:04","link":"https://www.chess.com/game/live/6017053070","moves":"1. d4 d5 2. Bf4 Nf6 3. e3 c5 4. Nc3 e6 5. Nb5 Na6 6. Nf3 Be7 7. c3 O-O 8. Bd3 Bd7 9. a4 c4 10. Bc2 Bxb5 11. axb5 Nc7 12. b6 axb6 13. Rxa8 Nxa8 14. O-O b5 15. Ne5 Nb6 16. g4 Nfd7 17. Qf3 Nxe5 18. Bxe5 Nd7 19. Bg3 b4 20. Ra1 bxc3 21. bxc3 b5 22. e4 Nf6 23. Ra7 b4 24. e5 Nd7 25. cxb4 Bxb4 26. Rb7 Be7 27. Qd1 Qc8 28. Qb1 Nb8 29. Rxe7 Nc6 30. Rb7 Nxd4 31. Rb6 Qc5 32. Rb8 Nxc2 33. Rxf8+ Qxf8 34. Qxc2 Qc5 35. Bf4 d4 36. Qe4 h6 37. Qa8+ Kh7 38. Qe4+ Kg8 39. h4 d3 40. Qa8+ Kh7 41. Qe4+ Kg8 42. Be3 Qd5 43. Qxd5 exd5 44. Kf1 c3 45. Ke1 d2+ 46. Kd1 Kf8 47. Bd4 Ke7 48. Bxc3 Ke6 49. Kxd2 f6 50. exf6 gxf6 51. Ke3 Kd6 52. Bxf6 Ke6 53. Bd4 Kd6 54. Kf4 Ke6 55. g5 hxg5+ 56. hxg5 Kf7 57. Kf5 Kg8 58. g6 Kf8 59. Kf6 Kg8 60. g7 Kh7 61. Kf7 Kh6 62. g8=Q Kh5 63. Bf6 Kh6 64. Qh8#"},{"id":"6009890435","site":"Chess.com","date":"2020.12.20","white":"enricotripoli","black":"SenseiDanya","result":"0-1","currentposition":"1r3rk1/4ppbp/Q5p1/p7/N1p2P1P/1P1B4/2PP2P1/qK1R3R w - -","eco":"B02","ecourl":"https://www.chess.com/openings/Alekhines-Defense-Samisch-Attack","whiteelo":"2191","blackelo":"2198","starttime":"00:26:51","endtime":"00:34:53","link":"https://www.chess.com/game/live/6009890435","moves":"1. e4 Nf6 2. e5 Nd5 3. Nc3 Nb6 4. a4 a5 5. Bb5 c6 6. Bd3 d5 7. Nce2 g6 8. b3 Bg7 9. Bb2 O-O 10. h4 c5 11. Nf4 Nc6 12. Nf3 Bg4 13. Qe2 Qc7 14. O-O-O Bxf3 15. Qxf3 Nxe5 16. Nxd5 Qd6 17. Bxe5 Qxe5 18. Nc3 c4 19. Qxb7 Rab8 20. f4 Qc5 21. Qa6 Qa3+ 22. Kb1 Nxa4 23. Nxa4 Qa1#"},{"id":"6009796921","site":"Chess.com","date":"2020.12.20","white":"dm85","black":"SenseiDanya","result":"0-1","currentposition":"8/5p1k/6p1/3Q4/P7/5qP1/8/3R2Kr w - -","eco":"C48","ecourl":"https://www.chess.com/openings/Four-Knights-Game-Spanish-Variation-Rubinstein-Accepted-Exchange-Variation...7.exf6-Qxf6-8.dxc3-Bc5","whiteelo":"2260","blackelo":"2190","starttime":"00:08:51","endtime":"00:18:42","link":"https://www.chess.com/game/live/6009796921","moves":"1. e4 e5 2. Nf3 Nc6 3. Nc3 Nf6 4. Bb5 Nd4 5. Nxd4 exd4 6. e5 dxc3 7. exf6 Qxf6 8. dxc3 Bc5 9. O-O O-O 10. Bd3 d6 11. Qh5 g6 12. Qh6 Re8 13. Bg5 Qg7 14. Qh4 h5 15. a4 a6 16. Rfe1 Be6 17. Bc4 Bxc4 18. Qxc4 Re5 19. Rxe5 Qxe5 20. Bf4 Qf5 21. b4 Ba7 22. Bg3 Re8 23. Qxc7 h4 24. Qxb7 Qe6 25. Rf1 hxg3 26. Qxa7 gxh2+ 27. Kxh2 Qe5+ 28. Kg1 Qxc3 29. Qxa6 Qxb4 30. Qb5 Qe4 31. c4 Re5 32. Qb8+ Kg7 33. Qxd6 Rg5 34. g3 Rh5 35. f3 Qxc4 36. Rd1 Qe2 37. Qd2 Qxf3 38. Qd4+ Kh7 39. Qd5 Rh1#"},{"id":"6009679902","site":"Chess.com","date":"2020.12.19","white":"SenseiDanya","black":"guildwars123","result":"1-0","currentposition":"r7/pp1R4/6pk/8/2pP4/P1P3N1/6PP/R5K1 b - -","eco":"E20","ecourl":"https://www.chess.com/openings/Nimzo-Indian-Defense-Kmoch-Variation-4...d5-5.a3","whiteelo":"2180","blackelo":"2206","starttime":"23:47:37","endtime":"23:55:17","link":"https://www.chess.com/game/live/6009679902","moves":"1. d4 Nf6 2. c4 e6 3. Nc3 Bb4 4. f3 d5 5. a3 Bxc3+ 6. bxc3 c5 7. cxd5 exd5 8. e3 O-O 9. Bd3 Re8 10. Ne2 c4 11. Bc2 Be6 12. O-O Nc6 13. Ng3 Ne7 14. e4 Ng6 15. e5 Nd7 16. f4 f5 17. exf6 Bf7 18. f5 Ngf8 19. fxg7 Kxg7 20. f6+ Kh8 21. Bh6 Nxf6 22. Bg5 N8d7 23. Qf3 Qb6 24. Bxf6+ Nxf6 25. Qxf6+ Qxf6 26. Rxf6 Kg7 27. Raf1 Re7 28. Rd6 Bg6 29. Bxg6 hxg6 30. Rxd5 Re3 31. Rd7+ Kh6 32. Rf3 Re1+ 33. Rf1 Ra1 34. Rxa1"},{"id":"6009457698","site":"Chess.com","date":"2020.12.19","white":"SenseiDanya","black":"x0Stark69","result":"1-0","currentposition":"3Q2k1/5p2/4p1pp/2q5/2P5/1B5P/5PP1/5RK1 b - -","eco":"B10","ecourl":"https://www.chess.com/openings/Caro-Kann-Defense-Two-Knights-Attack-3...dxe4-4.Nxe4","whiteelo":"2171","blackelo":"2135","starttime":"23:10:05","endtime":"23:20:07","link":"https://www.chess.com/game/live/6009457698","moves":"1. e4 c6 2. Nc3 d5 3. Nf3 dxe4 4. Nxe4 Bg4 5. Bc4 e6 6. h3 Bxf3 7. Qxf3 Nd7 8. d4 Ngf6 9. O-O Nxe4 10. Qxe4 Nf6 11. Qd3 h6 12. Bd2 Bd6 13. Rae1 Qc7 14. a4 Rd8 15. Qf3 Be7 16. c3 Qa5 17. Bb3 Qb6 18. Qd1 c5 19. dxc5 Bxc5 20. Re2 O-O 21. Qc2 Rd7 22. Ba2 Rfd8 23. Bb1 a5 24. Bf4 Bd6 25. Be3 Bc5 26. Bf4 Bd6 27. Bc1 Qc6 28. Rfe1 b5 29. axb5 Qxb5 30. c4 Qc6 31. b3 Bb4 32. Rf1 Bc5 33. Bf4 Bd6 34. Bc1 Bc5 35. Re5 Bd4 36. Rxa5 Rb8 37. Bf4 Rbd8 38. b4 Bb6 39. Rb5 Rd4 40. Rxb6 Qxb6 41. Be3 Qxb4 42. Bxd4 Rxd4 43. Ba2 Qc5 44. Qe2 Re4 45. Qf3 Rd4 46. Bb3 g6 47. Qxf6 Rd8 48. Qxd8+"},{"id":"6009321829","site":"Chess.com","date":"2020.12.19","white":"SenseiDanya","black":"georgigrigorov55","result":"1-0","currentposition":"2nbkr2/1R1b3p/4p1pQ/qP1pP3/3B3P/3B1N2/5PP1/6K1 b - -","eco":"C05","ecourl":"https://www.chess.com/openings/French-Defense-Tarrasch-Closed-4.e5-Nfd7-5.c3","whiteelo":"2164","blackelo":"2223","starttime":"22:48:22","endtime":"22:58:37","link":"https://www.chess.com/game/live/6009321829","moves":"1. e4 e6 2. d4 d5 3. Nd2 Nf6 4. e5 Nfd7 5. c3 c5 6. Bd3 Nc6 7. Ngf3 f6 8. Ng5 Nb6 9. Qh5+ Kd7 10. Ngf3 cxd4 11. cxd4 fxe5 12. dxe5 Qe8 13. Qg4 g6 14. O-O Bg7 15. Nb3 Kc7 16. Bf4 Bd7 17. Rac1 Rc8 18. Nbd4 Kb8 19. Nb5 Qe7 20. Nd6 Rc7 21. b4 a6 22. a4 Na7 23. Rxc7 Kxc7 24. b5 axb5 25. axb5 Kb8 26. Ra1 Nac8 27. Be3 Nxd6 28. Bxb6 Nc8 29. Qd4 Bf8 30. Ba7+ Kc7 31. Rc1+ Kd8 32. Bb6+ Ke8 33. Rc7 Qb4 34. Qe3 Be7 35. h4 Rf8 36. Bd4 Bd8 37. Rxb7 Qa5 38. Qh6"},{"id":"5994636361","site":"Chess.com","date":"2020.12.18","white":"mgokun","black":"SenseiDanya","result":"0-1","currentposition":"1b3rk1/1b4r1/1R2R3/p2p4/P2P1pp1/2PB2P1/1P3K2/8 w - -","eco":"A48","ecourl":"https://www.chess.com/openings/Torre-Attack-Fianchetto-Defense-4.e3","whiteelo":"2139","blackelo":"2154","starttime":"04:06:37","endtime":"04:16:50","link":"https://www.chess.com/game/live/5994636361","moves":"1. d4 Nf6 2. Nf3 g6 3. Bg5 Bg7 4. e3 O-O 5. Bc4 d6 6. c3 b6 7. Nbd2 Bb7 8. a4 a5 9. O-O Nbd7 10. Qb3 e6 11. Rfe1 h6 12. Bh4 g5 13. Bg3 Nh5 14. e4 Qf6 15. e5 Qg6 16. exd6 Nxg3 17. hxg3 cxd6 18. Bb5 Nf6 19. Rad1 Ng4 20. Nh2 Nxh2 21. Kxh2 h5 22. Be2 Rab8 23. Bf3 d5 24. Be2 g4 25. Nf1 f5 26. Qc2 Qf6 27. f4 h4 28. Kg1 hxg3 29. Nxg3 Qh4 30. Kf2 Qh6 31. Bd3 Qxf4+ 32. Kg1 Qxg3 33. Rxe6 Bh6 34. Qf2 Qxf2+ 35. Kxf2 Kg7 36. Rde1 Rf7 37. Rxb6 Rbf8 38. Ree6 Bf4 39. Rg6+ Kh8 40. g3 Bb8 41. Rh6+ Kg8 42. Rhg6+ Rg7 43. Rge6 f4"},{"id":"5994538676","site":"Chess.com","date":"2020.12.18","white":"SenseiDanya","black":"VanyaHargreeves","result":"1-0","currentposition":"8/8/8/1KP5/8/2kR3P/3R4/8 b - -","eco":"B10","ecourl":"https://www.chess.com/openings/Caro-Kann-Defense-Two-Knights-Attack","whiteelo":"2146","blackelo":"2241","starttime":"03:44:44","endtime":"03:55:05","link":"https://www.chess.com/game/live/5994538676","moves":"1. e4 c6 2. Nf3 d5 3. Nc3 Bg4 4. h3 Bxf3 5. Qxf3 e6 6. d4 dxe4 7. Nxe4 Qxd4 8. Bd3 Nf6 9. Be3 Qd8 10. O-O-O Nbd7 11. Ng5 Ne5 12. Qg3 Bd6 13. f4 Nxd3+ 14. Rxd3 Qc7 15. Rhd1 Nd5 16. Ne4 Bxf4 17. Bxf4 Qxf4+ 18. Qxf4 Nxf4 19. Rd7 Nd5 20. Rxb7 O-O 21. b3 a5 22. c4 Ne3 23. Rdd7 a4 24. Ng5 axb3 25. axb3 Rad8 26. Rdc7 Rd1+ 27. Kb2 Rg1 28. g4 Rg2+ 29. Kc3 Rg3 30. Kb4 Nc2+ 31. Kc5 Re3 32. Nxf7 h6 33. Nxh6+ Kh7 34. g5 Kg6 35. Rxg7+ Kh5 36. Ng4 Kh4 37. Nf6 Re5+ 38. Kd6 Rxg5 39. Rh7+ Kg3 40. Ne4+ Kf4 41. Nxg5 Kxg5 42. Kxc6 Kf4 43. Rhc7 Nd4+ 44. Kb6 Ne2 45. Rf7+ Ke3 46. Rxf8 Nc3 47. Re7 Kd4 48. Rxe6 Kd3 49. Re7 Kd2 50. Rd7+ Kc2 51. Rfd8 Na2 52. Rd3 Kb2 53. c5 Ka3 54. Kb5 Nb4 55. Rd2 Nc2 56. Rxc2 Kxb3 57. Rcd2 Kc3 58. R8d3#"},{"id":"5994503279","site":"Chess.com","date":"2020.12.18","white":"GMmauryahram","black":"SenseiDanya","result":"0-1","currentposition":"rnbq1rk1/pp4bp/2p3p1/3pppn1/3P4/2PB1P2/PP4PP/RNBQR1K1 w - -","eco":"B06","ecourl":"https://www.chess.com/openings/Modern-Defense-with-1-e4-2.d4-Bg7-3.Nf3-d6","whiteelo":"2111","blackelo":"2135","starttime":"03:37:04","endtime":"03:39:37","link":"https://www.chess.com/game/live/5994503279","moves":"1. e4 g6 2. d4 Bg7 3. Nf3 d6 4. Bc4 Nf6 5. O-O Nxe4 6. Re1 d5 7. Bb5+ c6 8. Bd3 f5 9. Ng5 O-O 10. c3 e5 11. f3 Nxg5"},{"id":"5994195715","site":"Chess.com","date":"2020.12.18","white":"spicyindianswag","black":"SenseiDanya","result":"0-1","currentposition":"8/5pkp/2P1p1p1/1p6/1p6/1P2PK1P/6P1/2q5 w - -","eco":"D19","ecourl":"https://www.chess.com/openings/Slav-Defense-Modern-Alapin-Variation-Czech-Classical-Dutch-Variation","whiteelo":"2093","blackelo":"2127","starttime":"02:30:37","endtime":"02:40:36","link":"https://www.chess.com/game/live/5994195715","moves":"1. d4 d5 2. c4 c6 3. Nf3 Nf6 4. Nc3 dxc4 5. a4 Bf5 6. e3 e6 7. Bxc4 Bb4 8. O-O Nbd7 9. h3 O-O 10. Nh4 Nb6 11. Bd3 Bxd3 12. Qxd3 a5 13. Nf3 c5 14. Nb5 Rc8 15. Bd2 Qd5 16. Bxb4 axb4 17. b3 Rfd8 18. a5 c4 19. Qd2 Qxb5 20. axb6 c3 21. Qc2 Qxb6 22. Ra4 g6 23. Ne5 Qd6 24. Nd3 Nd5 25. Rfa1 Rc7 26. Ra8 Rxa8 27. Rxa8+ Kg7 28. Ra4 b5 29. Ra5 Qb6 30. Ra2 Ra7 31. Rxa7 Qxa7 32. Nc5 Qa1+ 33. Kh2 Qb2 34. Qe4 Qxf2 35. Qe5+ Qf6 36. Qxf6+ Nxf6 37. Kg3 Ne4+ 38. Kf3 Nxc5 39. dxc5 c2 40. c6 c1=Q"},{"id":"5994112788","site":"Chess.com","date":"2020.12.18","white":"SenseiDanya","black":"grosbidepoilu","result":"1-0","currentposition":"5r2/1p1P3k/p4b2/5R2/4p3/7P/P4PP1/3R2K1 b - -","eco":"B51","ecourl":"https://www.chess.com/openings/Sicilian-Defense-Canal-Attack-3...Nd7-4.O-O","whiteelo":"2119","blackelo":"2125","starttime":"02:13:02","endtime":"02:21:41","link":"https://www.chess.com/game/live/5994112788","moves":"1. e4 c5 2. Nf3 d6 3. Bb5+ Nd7 4. O-O a6 5. Bxd7+ Qxd7 6. d4 cxd4 7. Qxd4 Nf6 8. c4 e5 9. Qd3 Be7 10. Nc3 O-O 11. Bg5 Qc6 12. Rac1 h6 13. Bxf6 Bxf6 14. Rfd1 Bg4 15. h3 Bxf3 16. Qxf3 Bg5 17. Nd5 Rae8 18. Rc3 f5 19. exf5 e4 20. Qg4 Bf6 21. Rg3 Be5 22. f6 g5 23. Qh5 Bxf6 24. Qxh6 Bg7 25. Rxg5 Qd7 26. Nf6+ Rxf6 27. Qxf6 Rf8 28. Qxd6 Qf7 29. Qd5 Qxd5 30. cxd5 Kh7 31. d6 Bxb2 32. d7 Bf6 33. Rf5"},{"id":"5994020422","site":"Chess.com","date":"2020.12.18","white":"SenseiDanya","black":"MisterNWA","result":"1-0","currentposition":"2r1rk1Q/pp1bppb1/3p1qpB/4n3/2P1P1P1/1NN2P2/PP6/1K3R1R b - -","eco":"E81","ecourl":"https://www.chess.com/openings/Kings-Indian-Defense-Samisch-Samisch-Gambit-7.Nge2","whiteelo":"2110","blackelo":"2105","starttime":"01:53:25","endtime":"02:01:11","link":"https://www.chess.com/game/live/5994020422","moves":"1. d4 Nf6 2. c4 g6 3. Nc3 Bg7 4. e4 d6 5. f3 O-O 6. Be3 c5 7. Nge2 cxd4 8. Nxd4 Nc6 9. Qd2 Re8 10. O-O-O Bd7 11. h4 Qa5 12. Kb1 Rac8 13. h5 Nxh5 14. Nb3 Qe5 15. g4 Ng3 16. Bf4 Nxf1 17. Rdxf1 Qe6 18. Qh2 Ne5 19. Qxh7+ Kf8 20. Bh6 Qf6 21. Qh8#"},{"id":"5987341761","site":"Chess.com","date":"2020.12.17","white":"Riomir","black":"SenseiDanya","result":"0-1","currentposition":"8/8/p7/P1N1p1k1/4Pp2/1P2nP1p/5K2/8 w - -","eco":"B31","ecourl":"https://www.chess.com/openings/Sicilian-Defense-Nyezhmetdinov-Rossolimo-Fianchetto-Variation-4.Bxc6-dxc6","whiteelo":"2303","blackelo":"2102","starttime":"08:24:44","endtime":"08:35:03","link":"https://www.chess.com/game/live/5987341761","moves":"1. e4 c5 2. Nf3 Nc6 3. Bb5 g6 4. Bxc6 dxc6 5. h3 Bg7 6. O-O e5 7. Re1 Ne7 8. c3 O-O 9. d3 b6 10. Na3 Ba6 11. Nc4 f6 12. a4 Qd7 13. a5 b5 14. Na3 Qe6 15. Be3 b4 16. Nc2 Rfd8 17. d4 Rd7 18. Qc1 b3 19. Na3 c4 20. Nb1 Rad8 21. Nbd2 Bb5 22. Nf1 Nc8 23. Ng3 Nd6 24. Kh2 a6 25. Re2 Bf8 26. Rd2 Nf7 27. dxe5 fxe5 28. Bb6 Rxd2 29. Nxd2 Rd3 30. Ndf1 Bh6 31. Be3 Bf8 32. Bb6 h5 33. f3 c5 34. Qe1 Qd6 35. Nh1 Bh6 36. Nf2 Bf4+ 37. Kh1 Ng5 38. Nxd3 cxd3 39. Nd2 Qe6 40. c4 Bxc4 41. Bxc5 Bb5 42. Be3 Nxh3 43. Bxf4 Nxf4 44. Rc1 Ne2 45. Rc7 Qf6 46. Qf2 Nd4 47. Rc8+ Kg7 48. Rc7+ Kh6 49. Qe3+ g5 50. Rb7 Qf4 51. Qxf4 gxf4 52. Kg1 Kg5 53. Kf2 h4 54. Rxb5 Nxb5 55. Nxb3 Nd6 56. Nc5 d2 57. Ke2 Nc4 58. b3 Ne3 59. Kxd2 Nxg2 60. Ke2 h3 61. Kf2 Ne3"},{"id":"5987288585","site":"Chess.com","date":"2020.12.17","white":"VanyaHargreeves","black":"SenseiDanya","result":"0-1","currentposition":"r1b1r1k1/pp3pbp/2pp1np1/4n3/N1PqP3/6PP/PP3P1K/R1BQRB2 w - -","eco":"E60","ecourl":"https://www.chess.com/openings/Kings-Indian-Defense-Fianchetto-Variation-4...O-O","whiteelo":"2246","blackelo":"2089","starttime":"08:12:27","endtime":"08:16:34","link":"https://www.chess.com/game/live/5987288585","moves":"1. d4 Nf6 2. c4 g6 3. g3 Bg7 4. Bg2 O-O 5. Nc3 d6 6. Nf3 Nbd7 7. O-O e5 8. e4 c6 9. h3 Qa5 10. Re1 exd4 11. Nxd4 Ne5 12. Bf1 Re8 13. Kh2 Qc5 14. Na4 Qxd4"},{"id":"5987206352","site":"Chess.com","date":"2020.12.17","white":"kushalbanerjee","black":"SenseiDanya","result":"1-0","currentposition":"8/4B3/3Q4/p1k5/3p2K1/3B4/1r3bP1/8 b - -","eco":"A46","ecourl":"https://www.chess.com/openings/Indian-Game-Knights-Variation","whiteelo":"2381","blackelo":"2077","starttime":"07:53:05","endtime":"08:03:02","link":"https://www.chess.com/game/live/5987206352","moves":"1. Nf3 Nf6 2. d4 g6 3. Ng5 h6 4. Nf3 Bg7 5. Ne5 d6 6. Nc4 O-O 7. Na5 c5 8. Nb3 cxd4 9. Qxd4 Nc6 10. Qa4 Bd7 11. e3 Rc8 12. Qh4 g5 13. Qc4 Ne5 14. Qe2 Bf5 15. Nc3 Ne4 16. Nb5 Qb6 17. N5d4 Bg6 18. f3 Nc5 19. h4 a5 20. hxg5 hxg5 21. Nxc5 dxc5 22. Nb5 c4 23. a4 Rfd8 24. Nd4 Nd3+ 25. cxd3 cxd3 26. Qd2 e5 27. Bxd3 exd4 28. e4 Rc5 29. Qe2 Rdc8 30. Bd2 Qxb2 31. Rb1 Qa2 32. Kf2 Qxa4 33. Rxb7 R5c7 34. Rxc7 Rxc7 35. Bxg5 Rb7 36. f4 Qa3 37. f5 Rb2 38. Bd2 Bh7 39. f6 Bxf6 40. Rxh7 Bg5 41. Rh5 Be3+ 42. Kg3 Kf8 43. Rh8+ Ke7 44. Qh5 Bf2+ 45. Kg4 Qd6 46. Bg5+ Kd7 47. e5 Qxe5 48. Qxf7+ Kc6 49. Rc8+ Kb6 50. Rb8+ Qxb8 51. Qe6+ Kc5 52. Be7+ Qd6 53. Qxd6#"},{"id":"5987138806","site":"Chess.com","date":"2020.12.17","white":"SenseiDanya","black":"gol-dad","result":"1-0","currentposition":"2q2k2/pp5p/5ppB/3Q4/3P4/P6P/1rrN1PP1/5RK1 b - -","eco":"B03","ecourl":"https://www.chess.com/openings/Alekhines-Defense-Exchange-Variation-5...cxd6-6.Nc3-g6-7.Be3","whiteelo":"2079","blackelo":"2056","starttime":"07:36:53","endtime":"07:43:45","link":"https://www.chess.com/game/live/5987138806","moves":"1. e4 Nf6 2. e5 Nd5 3. d4 d6 4. c4 Nb6 5. exd6 cxd6 6. Nc3 g6 7. Be3 Bg7 8. h3 O-O 9. Nf3 Nc6 10. Be2 e5 11. O-O e4 12. Nxe4 Bf5 13. Nc3 Nb4 14. Rc1 Rc8 15. a3 Nc2 16. Rxc2 Bxc2 17. Qxc2 Nxc4 18. Bxc4 Rxc4 19. Qb3 Qc8 20. Nd5 Re8 21. Bg5 Kf8 22. Nf6 Bxf6 23. Bxf6 Re6 24. Bg5 f6 25. Be3 d5 26. Nd2 Rb6 27. Qa2 Rc2 28. Qxd5 Rbxb2 29. Bh6+"},{"id":"5986986732","site":"Chess.com","date":"2020.12.17","white":"SenseiDanya","black":"fredham","result":"1-0","currentposition":"8/8/3K4/2Q5/p1k5/P7/2P5/8 b - -","eco":"C61","ecourl":"https://www.chess.com/openings/Ruy-Lopez-Opening-Birds-Defense-4.Nxd4-exd4-5.O-O-Bc5-6.d3","whiteelo":"2071","blackelo":"2032","starttime":"07:00:02","endtime":"07:08:40","link":"https://www.chess.com/game/live/5986986732","moves":"1. e4 e5 2. Nf3 Nc6 3. Bb5 Nd4 4. Nxd4 exd4 5. O-O Bc5 6. d3 Qh4 7. Nd2 c6 8. Bc4 d6 9. Nf3 Qh5 10. Ng5 Qxd1 11. Bxf7+ Ke7 12. Rxd1 h6 13. Bxg8 Rxg8 14. Nf3 Bg4 15. Re1 g5 16. Nd2 Raf8 17. Nb3 Bb6 18. Bd2 Bc7 19. e5 dxe5 20. Bb4+ Kd7 21. Bxf8 Rxf8 22. Nc5+ Kc8 23. Ne4 b6 24. f3 Be6 25. Re2 Bd5 26. Rae1 Bxe4 27. Rxe4 Kd7 28. h4 c5 29. hxg5 hxg5 30. Kf2 Rf4 31. Rxf4 gxf4 32. Rh1 Kc6 33. Rh7 a6 34. g4 fxg3+ 35. Kxg3 e4+ 36. Rxc7+ Kxc7 37. fxe4 Kd6 38. Kf4 Ke6 39. e5 b5 40. Ke4 a5 41. b3 a4 42. bxa4 bxa4 43. a3 Kd7 44. Kd5 Ke7 45. Kxc5 Ke6 46. Kxd4 Ke7 47. Kd5 Kd7 48. d4 Ke7 49. e6 Kf6 50. Kd6 Kf5 51. e7 Ke4 52. e8=Q+ Kxd4 53. Qe5+ Kc4 54. Qc5#"},{"id":"5986841186","site":"Chess.com","date":"2020.12.17","white":"SenseiDanya","black":"sandyrosechessfan","result":"1-0","currentposition":"5R2/5Rk1/1p1r2Pp/p2p2rP/6b1/1P4K1/P7/8 b - -","eco":"D10","ecourl":"https://www.chess.com/openings/Slav-Defense-3.Nc3","whiteelo":"2064","blackelo":"2041","starttime":"06:24:02","endtime":"06:33:50","link":"https://www.chess.com/game/live/5986841186","moves":"1. d4 d5 2. c4 c6 3. Nc3 Nf6 4. Nf3 e6 5. g3 Nbd7 6. Bg2 Be7 7. O-O O-O 8. b3 Re8 9. Bb2 b6 10. Nd2 Bb7 11. e4 dxe4 12. Ndxe4 g6 13. Qd2 Rc8 14. Rad1 Qc7 15. Rfe1 Red8 16. d5 cxd5 17. cxd5 exd5 18. Nb5 Qc2 19. Ned6 Qxd2 20. Rxd2 Bxd6 21. Nxd6 Rc7 22. Re7 Ba8 23. Rxf7 Rc6 24. Bxf6 Nxf6 25. Rxf6 Rcxd6 26. Rf4 Kg7 27. h4 Bc6 28. Rfd4 Kf7 29. f4 Ke6 30. Kf2 a5 31. g4 Kf6 32. Kg3 Re8 33. Kf2 Red8 34. g5+ Kf7 35. Bh3 Re8 36. f5 gxf5 37. Bxf5 Kg7 38. Kg3 Rf8 39. Bg4 Re8 40. Bf3 Re3 41. Kf4 Re8 42. h5 Rf8+ 43. Kg3 h6 44. g6 Rf5 45. Bg4 Rg5 46. Rf2 Bd7 47. Rf7+ Kg8 48. Rdf4 Bxg4 49. Rf8+ Kg7 50. R4f7#"},{"id":"5979027194","site":"Chess.com","date":"2020.12.16","white":"mellsipp","black":"SenseiDanya","result":"0-1","currentposition":"r1bqk2r/ppp1bppp/2n1p3/4P3/2B2n2/5N2/PPP2PPP/RN1Q1RK1 w kq -","eco":"B02","ecourl":"https://www.chess.com/openings/Alekhines-Defense-Normal-Variation","whiteelo":"2090","blackelo":"2056","starttime":"08:23:57","endtime":"08:25:52","link":"https://www.chess.com/game/live/5979027194","moves":"1. e4 Nf6 2. e5 Nd5 3. Nf3 d6 4. Bc4 e6 5. O-O Nc6 6. d4 dxe5 7. dxe5 Be7 8. Bf4 Nxf4"},{"id":"5979001056","site":"Chess.com","date":"2020.12.16","white":"SenseiDanya","black":"dobur","result":"1-0","currentposition":"rnbqkb1r/pppp1ppp/4p3/3nP3/2PP4/8/PP3PPP/RNBQKBNR b KQkq c3","eco":"B03","ecourl":"https://www.chess.com/openings/Alekhines-Defense-Normal-Variation-3.d4","whiteelo":"2047","blackelo":"2058","starttime":"08:17:54","endtime":"08:19:01","link":"https://www.chess.com/game/live/5979001056","moves":"1. e4 Nf6 2. e5 Nd5 3. d4 e6 4. c4"},{"id":"5978933171","site":"Chess.com","date":"2020.12.16","white":"Levansalamadze","black":"SenseiDanya","result":"0-1","currentposition":"r3r1k1/p4ppp/8/2n5/2p2P2/2P2R1P/PP1Nq2P/R1B4K w - -","eco":"B20","ecourl":"https://www.chess.com/openings/Sicilian-Defense-Bowdler-Attack","whiteelo":"2056","blackelo":"2038","starttime":"08:01:58","endtime":"08:07:47","link":"https://www.chess.com/game/live/5978933171","moves":"1. e4 c5 2. Bc4 Nc6 3. Nh3 Nf6 4. d3 e6 5. O-O d5 6. exd5 exd5 7. Bb5 Bxh3 8. gxh3 Be7 9. c3 O-O 10. Bxc6 bxc6 11. f4 Re8 12. Qf3 c4 13. dxc4 Bc5+ 14. Kh1 dxc4 15. Qxc6 Qd3 16. Nd2 Ne4 17. Rf3 Qe2 18. Qxc5 Nxc5"},{"id":"5978762512","site":"Chess.com","date":"2020.12.16","white":"SenseiDanya","black":"jameswagey","result":"1-0","currentposition":"8/p7/4R1Qp/2pp1p1k/3q1P2/7P/P1P3PK/8 b - -","eco":"C66","ecourl":"https://www.chess.com/openings/Ruy-Lopez-Opening-Berlin-Improved-Steinitz-Defense-5.d4","whiteelo":"2029","blackelo":"2037","starttime":"07:21:11","endtime":"07:29:25","link":"https://www.chess.com/game/live/5978762512","moves":"1. e4 e5 2. Nf3 Nc6 3. Bb5 Nf6 4. O-O d6 5. d4 exd4 6. Nxd4 Bd7 7. Nc3 Be7 8. Bxc6 bxc6 9. Qf3 O-O 10. Bg5 Ng4 11. Bxe7 Qxe7 12. h3 Ne5 13. Qg3 c5 14. Nd5 Qd8 15. Nf5 Bxf5 16. exf5 f6 17. Nf4 Qd7 18. Ne6 Rfe8 19. Rae1 Kh8 20. Re4 Rxe6 21. fxe6 Qxe6 22. f4 Qd5 23. Rfe1 Nd7 24. Re7 Qd4+ 25. Kh2 f5 26. Rxd7 Qxb2 27. Ree7 Rg8 28. Qe3 Qf6 29. Re8 h6 30. Rxc7 d5 31. Rcc8 Rxe8 32. Qxe8+ Kh7 33. Qg8+ Kg6 34. Re8 Kh5 35. Re6 Qd4 36. Qf7+ g6 37. Qxg6+"},{"id":"5978683235","site":"Chess.com","date":"2020.12.16","white":"SenseiDanya","black":"roychristian224","result":"1-0","currentposition":"4r2k/qp4pp/6R1/2b1Q3/P1B5/7P/1B4P1/3R3K b - -","eco":"B22","ecourl":"https://www.chess.com/openings/Sicilian-Defense-Alapin-Variation...3.d4-d5-4.exd5-exd5-5.Nf3","whiteelo":"2020","blackelo":"2004","starttime":"07:01:39","endtime":"07:09:54","link":"https://www.chess.com/game/live/5978683235","moves":"1. e4 c5 2. c3 e6 3. d4 d5 4. exd5 exd5 5. Nf3 Nf6 6. Bb5+ Nbd7 7. O-O Be7 8. dxc5 O-O 9. b4 a5 10. Bb2 axb4 11. cxb4 Nxc5 12. bxc5 Bxc5 13. Nbd2 Qb6 14. a4 Bg4 15. h3 Bh5 16. Qb3 Ne4 17. Nxe4 dxe4 18. Ne5 Rad8 19. Qg3 Bg6 20. Rad1 e3 21. fxe3 Bxe3+ 22. Kh1 Rde8 23. Nd7 Qa7 24. Nxf8 Rxf8 25. Qd6 Bc5 26. Qe5 f6 27. Bc4+ Kh8 28. Rxf6 Re8 29. Rxg6"},{"id":"5971058460","site":"Chess.com","date":"2020.12.15","white":"Tjuna","black":"SenseiDanya","result":"0-1","currentposition":"8/1p6/2p2k2/p1n1p3/2P1Pp2/1P3Pp1/P1r5/5KN1 w - -","eco":"E94","ecourl":"https://www.chess.com/openings/Kings-Indian-Defense-Orthodox-Variation...8.Nxd4-Re8-9.f3-c6-10.Kh1","whiteelo":"2053","blackelo":"2012","starttime":"09:21:28","endtime":"09:28:42","link":"https://www.chess.com/game/live/5971058460","moves":"1. d4 Nf6 2. c4 g6 3. Nc3 Bg7 4. e4 d6 5. Nf3 O-O 6. Be2 e5 7. O-O exd4 8. Nxd4 Re8 9. f3 c6 10. Kh1 Nh5 11. Be3 f5 12. Qd2 f4 13. Bf2 Be5 14. Nc2 Ng3+ 15. Kg1 Qh4 16. Bd4 Nxf1 17. Bxf1 Be6 18. Bxe5 dxe5 19. Qd6 Nd7 20. Qc7 Qd8 21. Qxd8 Raxd8 22. Kf2 Nc5 23. Rd1 Rxd1 24. Nxd1 Rd8 25. Ke1 a5 26. Nc3 Kf7 27. Be2 g5 28. h3 h5 29. b3 Kf6 30. Nd1 g4 31. hxg4 hxg4 32. Nf2 g3 33. Nd1 Rh8 34. Nc3 Rh2 35. Bf1 Bh3 36. Ne2 Bxg2 37. Ng1 Bxf1 38. Kxf1 Rxc2"},{"id":"5970963895","site":"Chess.com","date":"2020.12.15","white":"ChessLebaneseSalah","black":"SenseiDanya","result":"0-1","currentposition":"6k1/4p2p/3p2p1/1p1P4/pP6/3B1nP1/1P3r1P/1R5K w - -","eco":"B36","ecourl":"https://www.chess.com/openings/Sicilian-Defense-Open-Accelerated-Dragon-Maroczy-Bind-Formation-5...d6","whiteelo":"2038","blackelo":"2003","starttime":"08:49:13","endtime":"08:58:25","link":"https://www.chess.com/game/live/5970963895","moves":"1. e4 c5 2. Nf3 Nc6 3. d4 cxd4 4. Nxd4 g6 5. c4 d6 6. Be3 Bg7 7. Nc3 Nf6 8. Be2 O-O 9. O-O Bd7 10. Rc1 Nxd4 11. Bxd4 Bc6 12. f3 a5 13. Nd5 Bxd5 14. cxd5 Nd7 15. f4 Bxd4+ 16. Qxd4 Nc5 17. Bb5 a4 18. e5 Qb6 19. Bc4 Rac8 20. Kh1 Qb4 21. e6 b5 22. a3 Nb3 23. axb4 Nxd4 24. exf7+ Rxf7 25. Bd3 Rxc1 26. Rxc1 Rxf4 27. g3 Rf2 28. Rb1 Nf3"},{"id":"5970898646","site":"Chess.com","date":"2020.12.15","white":"PlatinUmba","black":"SenseiDanya","result":"0-1","currentposition":"2b2rk1/2p2p1p/3p2p1/2pPp3/QPP1P1Pq/P3bP2/4B1P1/R3NR1K w - -","eco":"A46","ecourl":"https://www.chess.com/openings/Indian-Game-Knights-Variation","whiteelo":"2033","blackelo":"1994","starttime":"08:33:47","endtime":"08:37:43","link":"https://www.chess.com/game/live/5970898646","moves":"1. Nf3 Nf6 2. d4 g6 3. c4 Bg7 4. Nc3 d6 5. e4 O-O 6. Be2 e5 7. d5 a5 8. O-O Na6 9. Ne1 Nc5 10. f3 Nh5 11. Be3 b6 12. a3 a4 13. Bxc5 bxc5 14. Nxa4 Bh6 15. b4 Be3+ 16. Kh1 Rxa4 17. Qxa4 Ng3+ 18. hxg3 Qg5 19. g4 Qh4#"},{"id":"5970848042","site":"Chess.com","date":"2020.12.15","white":"dobrin357","black":"SenseiDanya","result":"0-1","currentposition":"6k1/6p1/4p2p/2K2p2/8/3q4/8/8 w - -","eco":"B20","ecourl":"https://www.chess.com/openings/Sicilian-Defense-Bowdler-Attack","whiteelo":"2053","blackelo":"1985","starttime":"08:21:40","endtime":"08:28:32","link":"https://www.chess.com/game/live/5970848042","moves":"1. e4 c5 2. Bc4 Nc6 3. Nf3 e6 4. Nc3 Nf6 5. Qe2 d6 6. d3 Be7 7. O-O O-O 8. Nd1 d5 9. Bb3 Re8 10. c3 b6 11. Ng5 h6 12. Nh3 Ba6 13. f3 dxe4 14. fxe4 Bxd3 15. Qe3 Bxf1 16. Kxf1 c4 17. Bxc4 Qxd1+ 18. Qe1 Qxe1+ 19. Kxe1 Nxe4 20. Be3 Bc5 21. Bxc5 bxc5 22. Bb5 Rec8 23. Nf4 Rab8 24. Bxc6 Rxc6 25. Nd3 a5 26. Rc1 c4 27. Ne5 Rc7 28. Rc2 f6 29. Ng4 Rcb7 30. Re2 f5 31. Ne5 Rxb2 32. Rxb2 Rxb2 33. Nxc4 Rxa2 34. g3 a4 35. Kd1 Nxc3+ 36. Kc1 Rxh2 37. Ne5 a3 38. Nf3 a2 39. Nxh2 a1=Q+ 40. Kc2 Qa2+ 41. Kxc3 Qxh2 42. Kd4 Qxg3 43. Kc5 Qd3"},{"id":"5938621786","site":"Chess.com","date":"2020.12.11","white":"SenseiDanya","black":"ChessLebaneseSalah","result":"1-0","currentposition":"8/8/8/8/8/2K3P1/1Q3P2/k7 b - -","eco":"C10","ecourl":"https://www.chess.com/openings/French-Defense-Rubinstein-Variation-4.Nxe4","whiteelo":"1975","blackelo":"2109","starttime":"07:34:40","endtime":"07:45:09","link":"https://www.chess.com/game/live/5938621786","moves":"1. e4 e6 2. d4 d5 3. Nd2 dxe4 4. Nxe4 Nf6 5. Nxf6+ gxf6 6. Nf3 b6 7. Bd3 Bb7 8. Qe2 Nc6 9. Ba6 Nxd4 10. Nxd4 Bxa6 11. Qxa6 Qxd4 12. O-O Qd7 13. Bf4 Rg8 14. Rad1 Qc6 15. Bg3 Bd6 16. Rd3 Bxg3 17. hxg3 Rg5 18. Rf3 Ra5 19. Qd3 f5 20. Re1 Rd8 21. Qe3 Qxc2 22. Qg5 Qd2 23. Rfe3 Rd6 24. Qg8+ Ke7 25. Qxh7 Qxb2 26. Qg8 Rxa2 27. Qg5+ Qf6 28. Qf4 Qb2 29. Qh4+ Kd7 30. Rf3 Qd2 31. Rf1 Qd5 32. Qf6 Qe4 33. Qxf7+ Kc6 34. Rc3+ Kb5 35. Qxc7 Rc6 36. Qd7 Qd5 37. Rb1+ Ka5 38. Qxc6 Qxc6 39. Rxc6 Ka6 40. Rxe6 Ra5 41. Ree1 Rc5 42. Ra1+ Kb7 43. Rac1 Kc6 44. Rxc5+ Kxc5 45. Re5+ Kc4 46. Rxf5 b5 47. g4 b4 48. Rf8 Kc3 49. Rb8 b3 50. g5 b2 51. g6 Kc2 52. g7 b1=Q+ 53. Rxb1 Kxb1 54. g8=Q a5 55. Qb3+ Ka1 56. g3 a4 57. Qxa4+ Kb1 58. Qc4 Kb2 59. Qd3 Ka1 60. Qd2 Kb1 61. Kg2 Ka1 62. Kf3 Kb1 63. Ke3 Ka1 64. Kd3 Kb1 65. Kc3 Ka1 66. Qb2#"},{"id":"5938544567","site":"Chess.com","date":"2020.12.11","white":"SenseiDanya","black":"aposbapa","result":"1-0","currentposition":"r1b1R3/4kp2/p2p1N2/1pnPp1B1/2p1P3/2P3P1/1qBK1P2/8 b - -","eco":"B22","ecourl":"https://www.chess.com/openings/Sicilian-Defense-Alapin-Variation-2...e6-3.d4","whiteelo":"1964","blackelo":"2053","starttime":"07:16:00","endtime":"07:23:24","link":"https://www.chess.com/game/live/5938544567","moves":"1. e4 c5 2. c3 e6 3. d4 a6 4. d5 d6 5. Nf3 e5 6. Bd3 h6 7. Nbd2 g5 8. Nf1 g4 9. Ng1 h5 10. Ne3 Ne7 11. h3 gxh3 12. Nxh3 Ng6 13. Nf5 Be7 14. Ng7+ Kf8 15. Nxh5 Nh4 16. g3 Ng6 17. Qf3 Nd7 18. Be3 b5 19. O-O-O c4 20. Bc2 Qa5 21. Ng5 Bxg5 22. Bxg5 Qxa2 23. Nf6 Rxh1 24. Rxh1 Nc5 25. Qh5 Qa1+ 26. Kd2 Qxb2 27. Qh8+ Nxh8 28. Rxh8+ Ke7 29. Re8#"},{"id":"5938484875","site":"Chess.com","date":"2020.12.11","white":"SenseiDanya","black":"Budihartonomsp","result":"1-0","currentposition":"r3r1k1/7p/pB1p1pp1/1b1Pp3/2p1PnPQ/2P4P/1PB2P2/R4RK1 b - -","eco":"B22","ecourl":"https://www.chess.com/openings/Sicilian-Defense-Alapin-Variation-2...e6-3.d4","whiteelo":"1954","blackelo":"2037","starttime":"07:00:55","endtime":"07:07:42","link":"https://www.chess.com/game/live/5938484875","moves":"1. e4 c5 2. c3 e6 3. d4 a6 4. d5 d6 5. Nf3 e5 6. Bd3 Bg4 7. Nbd2 Nf6 8. Nf1 Be7 9. Ng3 b5 10. h3 Bd7 11. a4 c4 12. Bc2 O-O 13. axb5 Bxb5 14. O-O Re8 15. Nf5 Bf8 16. Bg5 Nbd7 17. Nh2 Qb6 18. Ng4 Nxg4 19. Qxg4 g6 20. Nh6+ Bxh6 21. Bxh6 Nf6 22. Qh4 Nh5 23. g4 f6 24. Be3 Nf4 25. Bxb6"},{"id":"5938375354","site":"Chess.com","date":"2020.12.11","white":"SenseiDanya","black":"rayan147","result":"1-0","currentposition":"7k/7p/p1BbP1p1/1p1P4/1P2K1P1/P6P/8/8 b - -","eco":"B22","ecourl":"https://www.chess.com/openings/Sicilian-Defense-Alapin-Variation-2...d6","whiteelo":"1944","blackelo":"1925","starttime":"06:33:29","endtime":"06:43:42","link":"https://www.chess.com/game/live/5938375354","moves":"1. e4 c5 2. c3 d6 3. d4 cxd4 4. cxd4 Nf6 5. Nc3 Nc6 6. Nf3 g6 7. h3 Bg7 8. Be3 O-O 9. Bd3 Nb4 10. Be2 a6 11. O-O d5 12. e5 Ne4 13. Nxe4 dxe4 14. Nd2 Bf5 15. g4 Be6 16. Nxe4 Rc8 17. a3 Nc2 18. Rc1 Nxe3 19. fxe3 Bd5 20. Bf3 f5 21. exf6 exf6 22. Rxc8 Qxc8 23. Nxf6+ Rxf6 24. Bxd5+ Kh8 25. Rxf6 Bxf6 26. Kg2 Bg5 27. Qf3 b5 28. b4 Qc2+ 29. Qf2 Qc8 30. e4 Qd8 31. Qf7 Bh4 32. e5 Be7 33. Kf3 Bg5 34. Ke4 Bh4 35. e6 Be7 36. Bc6 Bf6 37. d5 Be7 38. Qe8+ Qxe8 39. Bxe8 Bd6 40. Bc6"},{"id":"5930953026","site":"Chess.com","date":"2020.12.10","white":"Kadu_de_Souza","black":"SenseiDanya","result":"0-1","currentposition":"8/p1p3kp/2n3p1/3Bn3/8/2P5/Pr4PP/4R1K1 w - -","eco":"B09","ecourl":"https://www.chess.com/openings/Pirc-Defense-Main-Line-Austrian-Attack-4...Bg7","whiteelo":"1943","blackelo":"1936","starttime":"08:58:23","endtime":"09:04:47","link":"https://www.chess.com/game/live/5930953026","moves":"1. e4 g6 2. d4 Bg7 3. Nc3 d6 4. f4 Nf6 5. Nf3 O-O 6. e5 dxe5 7. fxe5 Nd5 8. Bc4 Be6 9. Ng5 Nxc3 10. Nxe6 Nxd1 11. Nxd8 Rxd8 12. O-O Rxd4 13. Bxf7+ Kh8 14. c3 Rd8 15. Bg5 Nxb2 16. Bxe7 Rc8 17. Rab1 Nc6 18. Bf6 Nd3 19. Rxb7 Ndxe5 20. Bxg7+ Kxg7 21. Bd5 Rab8 22. Rxb8 Rxb8 23. Re1 Rb2"},{"id":"5930854169","site":"Chess.com","date":"2020.12.10","white":"mengermania","black":"SenseiDanya","result":"0-1","currentposition":"4r1k1/pp3p2/2bR2pQ/7p/7q/2P2P2/P3r1P1/3R3K w - -","eco":"E92","ecourl":"https://www.chess.com/openings/Kings-Indian-Defense-Gligoric-System-7...exd4","whiteelo":"1953","blackelo":"1927","starttime":"08:35:53","endtime":"08:42:09","link":"https://www.chess.com/game/live/5930854169","moves":"1. d4 Nf6 2. c4 g6 3. Nc3 Bg7 4. e4 d6 5. Nf3 O-O 6. Be2 e5 7. Be3 exd4 8. Nxd4 Re8 9. f3 c6 10. Qd2 d5 11. cxd5 cxd5 12. e5 Rxe5 13. O-O Nc6 14. Rad1 Bd7 15. Bf4 Re8 16. Kh1 Nxd4 17. Qxd4 Nh5 18. Qd2 Nxf4 19. Qxf4 Bxc3 20. bxc3 Rxe2 21. Rxd5 Qe7 22. h4 h5 23. Rfd1 Bc6 24. Rd6 Re8 25. Qh6 Qxh4+"},{"id":"5930756903","site":"Chess.com","date":"2020.12.10","white":"dusan555","black":"SenseiDanya","result":"0-1","currentposition":"8/7p/4p3/3pP3/2pP1k2/2q5/4K3/8 w - -","eco":"B22","ecourl":"https://www.chess.com/openings/Sicilian-Defense-Alapin-Variation-2...Nc6-3.Nf3","whiteelo":"1910","blackelo":"1918","starttime":"08:13:01","endtime":"08:23:14","link":"https://www.chess.com/game/live/5930756903","moves":"1. e4 c5 2. Nf3 Nc6 3. c3 Nf6 4. Bd3 d5 5. e5 Ng4 6. Bb5 Bd7 7. d4 Ncxe5 8. Nxe5 Nxe5 9. Bxd7+ Nxd7 10. O-O e6 11. f4 g6 12. Be3 c4 13. Nd2 Bg7 14. Nf3 O-O 15. Ne5 Nf6 16. Bf2 Ne4 17. Be1 f6 18. Ng4 f5 19. Ne5 Bxe5 20. fxe5 Qg5 21. Qf3 b5 22. Rd1 a5 23. Kh1 Rab8 24. Rg1 b4 25. g4 fxg4 26. Qxg4 Qxg4 27. Rxg4 bxc3 28. bxc3 Rb2 29. Rg2 Rf1+ 30. Rg1 Rxg1+ 31. Kxg1 Rxa2 32. Rb1 a4 33. Kf1 a3 34. Rb8+ Kg7 35. Ra8 g5 36. h4 g4 37. h5 g3 38. Ra6 g2+ 39. Kg1 Ng5 40. h6+ Kf7 41. Ra7+ Kg6 42. Rg7+ Kxh6 43. Rxg5 Kxg5 44. Bf2 Rxf2 45. Kxf2 a2 46. Kxg2 a1=Q 47. Kf2 Qxc3 48. Ke2 Kf4"},{"id":"5930689030","site":"Chess.com","date":"2020.12.10","white":"SenseiDanya","black":"agrotis","result":"1-0","currentposition":"r3r1k1/pp3ppp/8/3p2B1/3q4/4R3/PPP2QPP/5RK1 b - -","eco":"B01","ecourl":"https://www.chess.com/openings/Scandinavian-Defense-Mieses-Kotrc-Variation-3.Nc3-Qd8","whiteelo":"1910","blackelo":"1922","starttime":"07:56:23","endtime":"08:02:53","link":"https://www.chess.com/game/live/5930689030","moves":"1. e4 d5 2. exd5 Qxd5 3. Nc3 Qd8 4. d4 Nf6 5. Nf3 Bg4 6. Be2 e6 7. O-O c6 8. Ne5 Bxe2 9. Qxe2 Bd6 10. Bg5 O-O 11. f4 Nbd7 12. f5 exf5 13. Rxf5 Re8 14. Raf1 Nxe5 15. dxe5 Bxe5 16. Rxe5 Qd4+ 17. Re3 Nd5 18. Nxd5 cxd5 19. Qf2"},{"id":"5930613572","site":"Chess.com","date":"2020.12.10","white":"SenseiDanya","black":"ions26","result":"1-0","currentposition":"8/8/8/k1K5/8/8/1Q6/8 b - -","eco":"B07","ecourl":"https://www.chess.com/openings/Pirc-Defense-2.d4-c6","whiteelo":"1901","blackelo":"1881","starttime":"07:37:30","endtime":"07:47:45","link":"https://www.chess.com/game/live/5930613572","moves":"1. e4 c6 2. d4 d6 3. Nc3 e6 4. Nf3 a6 5. Bd3 h6 6. O-O b6 7. Be3 Bb7 8. d5 cxd5 9. exd5 e5 10. Nd2 g5 11. a4 Nd7 12. Nc4 Ngf6 13. Bf5 Rg8 14. Re1 Be7 15. a5 bxa5 16. Nxa5 Qc7 17. Ra4 h5 18. Qa1 Bxd5 19. Nxd5 Nxd5 20. Rc4 Qb8 21. Nc6 Qb7 22. Qa4 Nxe3 23. Rxe3 Kf8 24. Rb3 Nb6 25. Qb4 d5 26. Nxe7 dxc4 27. Nxg8+ Kxg8 28. Rg3 g4 29. h3 Rb8 30. hxg4 h4 31. Rh3 Qd5 32. Rxh4 Qd1+ 33. Kh2 Qc1 34. Qe7 Qf4+ 35. Kh3 Nd5 36. Qd6 Re8 37. Qxd5 Qxf2 38. Qf3 Qxf3+ 39. gxf3 Kg7 40. b3 cxb3 41. Rh7+ Kf6 42. cxb3 Rb8 43. Rh6+ Ke7 44. Rxa6 Rxb3 45. Be4 Rb8 46. Ra7+ Kd6 47. Rb7 Rh8+ 48. Kg3 Rf8 49. g5 f5 50. gxf6 Rxf6 51. Rb6+ Ke7 52. Rxf6 Kxf6 53. Kg4 Ke6 54. Kg5 Ke7 55. Kf5 Kd6 56. Kf6 Kc5 57. Kxe5 Kb6 58. f4 Kc7 59. Ke6 Kd8 60. Kf7 Kd7 61. f5 Kd6 62. f6 Ke5 63. Kg7 Kxe4 64. f7 Kf5 65. f8=Q+ Ke6 66. Qf6+ Kd5 67. Qe7 Kd4 68. Kf6 Kd5 69. Qe5+ Kc6 70. Ke6 Kb6 71. Qc3 Kb5 72. Kd5 Ka4 73. Qb2 Ka5 74. Kc5"},{"id":"5930610989","site":"Chess.com","date":"2020.12.10","white":"SenseiDanya","black":"Malush13","result":"1-0","currentposition":"rnbqkbnr/pppppppp/8/8/4P3/8/PPPP1PPP/RNBQKBNR b KQkq e3","eco":"B00","ecourl":"https://www.chess.com/openings/Kings-Pawn-Opening","whiteelo":"1893","blackelo":"1885","starttime":"07:36:57","endtime":"07:37:19","link":"https://www.chess.com/game/live/5930610989","moves":"1. e4"},{"id":"5922626127","site":"Chess.com","date":"2020.12.09","white":"HurohutteChakma","black":"SenseiDanya","result":"0-1","currentposition":"rnbqkbn1/ppp2pp1/8/3pp3/8/1PPPPPp1/P6r/RNBQKBNR w KQq -","eco":"A00","ecourl":"https://www.chess.com/openings/Kings-Fianchetto-Opening-1...e5","whiteelo":"1873","blackelo":"1885","starttime":"07:04:15","endtime":"07:07:20","link":"https://www.chess.com/game/live/5922626127","moves":"1. g3 e5 2. f3 d5 3. e3 h5 4. d3 h4 5. c3 hxg3 6. b3 Rxh2"},{"id":"5922550583","site":"Chess.com","date":"2020.12.09","white":"staxxknight","black":"SenseiDanya","result":"0-1","currentposition":"2r3k1/3p3p/4p2b/4P3/5P2/P3pqP1/R6K/1R6 w - -","eco":"B21","ecourl":"https://www.chess.com/openings/Sicilian-Defense-Smith-Morra-Gambit-Declined-Alapin-Formation","whiteelo":"1918","blackelo":"1877","starttime":"06:45:25","endtime":"06:55:06","link":"https://www.chess.com/game/live/5922550583","moves":"1. e4 c5 2. d4 cxd4 3. c3 Nf6 4. e5 Nd5 5. Qxd4 e6 6. Nf3 Nc6 7. Qe4 f5 8. Qe2 b5 9. g3 a5 10. Bg2 Ba6 11. Nh4 Nde7 12. O-O Qc7 13. Re1 g6 14. b4 Bg7 15. Bb2 O-O 16. Nf3 axb4 17. cxb4 Nxb4 18. Nc3 Qa5 19. h4 Nbd5 20. Nxd5 Nxd5 21. h5 b4 22. Qd2 gxh5 23. Qg5 Qd8 24. Qxh5 Qe8 25. Qh4 Qg6 26. Rac1 Rac8 27. Nd4 Nc3 28. a3 Bh6 29. Rc2 Bd3 30. Bxc3 bxc3 31. Ra2 c2 32. Nxc2 Bxc2 33. f4 Be4 34. Bxe4 fxe4 35. Kh2 Rf5 36. Rb1 Rh5 37. Qxh5 Qxh5+ 38. Kg2 Qf3+ 39. Kh2 e3"},{"id":"5922476743","site":"Chess.com","date":"2020.12.09","white":"LoveFades","black":"SenseiDanya","result":"0-1","currentposition":"r5k1/7p/6p1/8/5P2/7P/r3R1PK/8 w - -","eco":"A48","ecourl":"https://www.chess.com/openings/Indian-Game-Knights-Variation-East-Indian-Defense-3.e3-Bg7","whiteelo":"1831","blackelo":"1868","starttime":"06:27:07","endtime":"06:37:07","link":"https://www.chess.com/game/live/5922476743","moves":"1. d4 Nf6 2. Nf3 g6 3. e3 Bg7 4. c3 O-O 5. Nbd2 d6 6. h3 Nc6 7. b4 e5 8. Bb2 Re8 9. Bb5 Bd7 10. O-O Nxd4 11. exd4 Bxb5 12. c4 Bc6 13. dxe5 Nd7 14. Re1 Nxe5 15. Nxe5 dxe5 16. b5 Bd7 17. Nf3 f6 18. Qd5+ Be6 19. Qxb7 Bxc4 20. Rad1 Qb8 21. Qxb8 Raxb8 22. a4 c6 23. Rd7 cxb5 24. Rxa7 bxa4 25. Ba3 Ra8 26. Rc7 Rec8 27. Re7 Bf8 28. Nd2 Bxe7 29. Bxe7 a3 30. Nxc4 Rxc4 31. Bxf6 a2 32. Bxe5 Rb4 33. Kh2 Rb1 34. Re2 a1=Q 35. Bxa1 Rbxa1 36. f4 R1a2"},{"id":"5922405198","site":"Chess.com","date":"2020.12.09","white":"SenseiDanya","black":"Donkongee","result":"1-0","currentposition":"2kr1b1r/pp3ppp/1qn2n2/8/NP1p1Bb1/P3PN2/2P2PPP/1R1QKB1R b K -","eco":"A40","ecourl":"https://www.chess.com/openings/Englund-Gambit-2.dxe5-Nc6-3.Nf3","whiteelo":"1860","blackelo":"1828","starttime":"06:09:29","endtime":"06:17:09","link":"https://www.chess.com/game/live/5922405198","moves":"1. d4 e5 2. dxe5 Nc6 3. Nf3 d6 4. Bf4 Bg4 5. exd6 cxd6 6. Nc3 Nf6 7. e3 d5 8. a3 Qb6 9. Rb1 O-O-O 10. b4 d4 11. Na4"},{"id":"5922322547","site":"Chess.com","date":"2020.12.09","white":"SenseiDanya","black":"bsngsu","result":"1-0","currentposition":"3R4/p3kr1n/2pQ3p/4P1p1/7P/8/q1P3PK/8 b - -","eco":"B07","ecourl":"https://www.chess.com/openings/Pirc-Defense-2.d4-c6","whiteelo":"1852","blackelo":"1856","starttime":"05:49:08","endtime":"05:58:23","link":"https://www.chess.com/game/live/5922322547","moves":"1. e4 c6 2. d4 d6 3. Nc3 Nd7 4. f4 Qc7 5. Nf3 e5 6. Bc4 h6 7. O-O Ngf6 8. fxe5 dxe5 9. d5 Be7 10. dxc6 bxc6 11. Be3 O-O 12. h3 Rd8 13. Qe1 Nf8 14. Qg3 Be6 15. Bxe6 Nxe6 16. Qxe5 Bd6 17. Qf5 Nh7 18. e5 Bc5 19. Bxc5 Nxc5 20. Rad1 Ne6 21. Ne4 Rxd1 22. Rxd1 Qb6+ 23. Kh2 Qxb2 24. Rd7 Rf8 25. Nd6 Neg5 26. Nxg5 Nxg5 27. h4 g6 28. Qf6 Nh7 29. Qf4 g5 30. Qf5 Qxa2 31. Nxf7 Rxf7 32. Qg6+ Kf8 33. Rd8+ Ke7 34. Qd6#"},{"id":"5914794898","site":"Chess.com","date":"2020.12.08","white":"SenseiDanya","black":"mhj76","result":"1-0","currentposition":"8/5Rpk/p6p/1p3Q2/4P3/P1q5/4rPPP/5RK1 b - -","eco":"B22","ecourl":"https://www.chess.com/openings/Sicilian-Defense-Alapin-Variation-2...d6","whiteelo":"1843","blackelo":"1992","starttime":"08:26:12","endtime":"08:33:42","link":"https://www.chess.com/game/live/5914794898","moves":"1. e4 c5 2. c3 d6 3. d4 Nf6 4. Bd3 Nc6 5. Nf3 e6 6. O-O Be7 7. Bg5 O-O 8. Nbd2 cxd4 9. cxd4 e5 10. d5 Nb4 11. Be2 Nfxd5 12. Bxe7 Nxe7 13. Nc4 Be6 14. Nxd6 Qc7 15. Nb5 Qb6 16. Nxe5 a6 17. Nc3 Rad8 18. Qa4 Qc5 19. a3 Qxe5 20. Qxb4 b5 21. Qxe7 Rd2 22. Rad1 Rxb2 23. Rd8 h6 24. Rxf8+ Kh7 25. Rxf7 Qxc3 26. Qxe6 Rxe2 27. Qf5+"},{"id":"5914731665","site":"Chess.com","date":"2020.12.08","white":"EdawgChessMood","black":"SenseiDanya","result":"0-1","currentposition":"3r2rk/p1p4p/1p6/8/8/8/PP3n1B/6RK w - -","eco":"A40","ecourl":"https://www.chess.com/openings/Modern-Defense-with-1-d4","whiteelo":"1893","blackelo":"1831","starttime":"08:10:32","endtime":"08:20:31","link":"https://www.chess.com/game/live/5914731665","moves":"1. d4 g6 2. Bf4 Bg7 3. e3 d6 4. Nf3 Nd7 5. Nbd2 e5 6. dxe5 dxe5 7. Bg3 Qe7 8. c3 Ngf6 9. Bc4 O-O 10. O-O b6 11. Re1 Bb7 12. h3 Rad8 13. Qc2 Nh5 14. Bh2 Nc5 15. Nf1 Bxf3 16. gxf3 Qh4 17. Be2 Qxh3 18. Ng3 Nxg3 19. Bxg3 f5 20. Bf1 Qh5 21. f4 g5 22. Qe2 Qg6 23. fxg5 Qxg5 24. Bg2 f4 25. Qc4+ Kh8 26. exf4 exf4 27. Bh2 f3 28. Qf1 Rg8 29. Kh1 fxg2+ 30. Qxg2 Qxg2+ 31. Kxg2 Bxc3+ 32. Kh1 Bxe1 33. Rxe1 Nd3 34. Rg1 Nxf2#"},{"id":"5914721465","site":"Chess.com","date":"2020.12.08","white":"Nonoy92","black":"SenseiDanya","result":"0-1","currentposition":"rnbqk1nr/ppppppbp/6p1/8/3PP3/8/PPP2PPP/RNBQKBNR w KQkq -","eco":"B06","ecourl":"https://www.chess.com/openings/Modern-Defense-with-1-e4-2.d4-Bg7","whiteelo":"1848","blackelo":"1821","starttime":"08:08:06","endtime":"08:10:30","link":"https://www.chess.com/game/live/5914721465","moves":"1. e4 g6 2. d4 Bg7"},{"id":"5914695254","site":"Chess.com","date":"2020.12.08","white":"SenseiDanya","black":"marko981","result":"1-0","currentposition":"rnb2rk1/pp3p1p/2p1pBp1/8/2N5/5Q2/PPP2PPP/R4RK1 b - -","eco":"B06","ecourl":"https://www.chess.com/openings/Modern-Defense-Standard-Line-3...c6","whiteelo":"1812","blackelo":"1776","starttime":"08:01:06","endtime":"08:04:06","link":"https://www.chess.com/game/live/5914695254","moves":"1. e4 g6 2. d4 Bg7 3. Nc3 c6 4. Bc4 e6 5. e5 d5 6. exd6 Qxd6 7. Nf3 Nf6 8. O-O Nd5 9. Ne4 Qd8 10. Bg5 Nf6 11. Ne5 O-O 12. Qf3 Qxd4 13. Nxf6+ Bxf6 14. Bxf6 Qxc4 15. Nxc4"},{"id":"5914662573","site":"Chess.com","date":"2020.12.08","white":"SenseiDanya","black":"darkjack","result":"1-0","currentposition":"r2qr1k1/ppp1bp1p/2n5/4PQ2/8/1N1B4/PPP3PP/R1B3K1 b - -","eco":"B07","ecourl":"https://www.chess.com/openings/Pirc-Defense-2.d4-Nf6-3.Nc3","whiteelo":"1805","blackelo":"1767","starttime":"07:51:19","endtime":"07:56:27","link":"https://www.chess.com/game/live/5914662573","moves":"1. e4 d6 2. d4 Nf6 3. Nc3 e5 4. Nf3 exd4 5. Nxd4 Be7 6. Bd3 Nc6 7. Nb3 O-O 8. O-O Be6 9. f4 Re8 10. Qf3 d5 11. e5 Ne4 12. Nxe4 dxe4 13. Qxe4 g6 14. f5 Bxf5 15. Rxf5 gxf5 16. Qxf5"},{"id":"5913987252","site":"Chess.com","date":"2020.12.08","white":"SenseiDanya","black":"remigiochess2017","result":"1-0","currentposition":"8/8/2k2p2/3pbRp1/3B2P1/1PPK3P/8/8 b - -","eco":"C00","ecourl":"https://www.chess.com/openings/Pirc-Defense-Small-Center-Defense","whiteelo":"1798","blackelo":"1816","starttime":"04:42:08","endtime":"04:48:58","link":"https://www.chess.com/game/live/5913987252","moves":"1. e4 e6 2. d4 d6 3. Nc3 Nd7 4. f4 a6 5. Nf3 b6 6. Bd3 Bb7 7. O-O h6 8. e5 d5 9. f5 Qe7 10. fxe6 Qxe6 11. Ne2 O-O-O 12. Nf4 Qe8 13. Qe2 Nb8 14. e6 f6 15. Ng6 Bd6 16. Nxh8 Ne7 17. Nf7 Nbc6 18. c3 Kb8 19. Nxd8 Qxd8 20. Bxa6 Nf5 21. Bxb7 Kxb7 22. a4 g5 23. a5 Nxa5 24. Rxa5 bxa5 25. Qb5+ Kc8 26. Qxa5 c6 27. Qxd8+ Kxd8 28. Nxg5 hxg5 29. Rxf5 Ke7 30. g4 Kxe6 31. b3 c5 32. dxc5 Bxc5+ 33. Kf1 Bd6 34. h3 Bg3 35. Ke2 Be5 36. Kd3 Kd6 37. Be3 Kc6 38. Bd4"},{"id":"5913927782","site":"Chess.com","date":"2020.12.08","white":"dionyreyes","black":"SenseiDanya","result":"0-1","currentposition":"r1b2rk1/pp5p/3p2p1/2pN2P1/2PbPp2/3P3q/PP1Q3K/R4R2 w - -","eco":"B20","ecourl":"https://www.chess.com/openings/Sicilian-Defense-Staunton-Cochrane-Variation","whiteelo":"1757","blackelo":"1789","starttime":"04:28:21","endtime":"04:32:20","link":"https://www.chess.com/game/live/5913927782","moves":"1. e4 c5 2. c4 Nc6 3. d3 g6 4. Nc3 Bg7 5. Be3 d6 6. h3 e6 7. Nge2 Nge7 8. g4 Nd4 9. Bg2 Nec6 10. Qd2 O-O 11. O-O f5 12. f4 fxg4 13. hxg4 Qh4 14. g5 e5 15. Bf2 Qg4 16. Kh2 exf4 17. Nxd4 Nxd4 18. Bxd4 Bxd4 19. Nd5 Qh4+ 20. Bh3 Qxh3#"},{"id":"5913858765","site":"Chess.com","date":"2020.12.08","white":"SenseiDanya","black":"Pinoy2its","result":"1-0","currentposition":"r4b1r/5Qp1/1qbkp2p/p4p2/1ppP1B2/2P5/PP3PPP/R3R1K1 b - -","eco":"C02","ecourl":"https://www.chess.com/openings/French-Defense-Advance-Variation-3...c5-4.c3","whiteelo":"1781","blackelo":"1745","starttime":"04:12:39","endtime":"04:16:55","link":"https://www.chess.com/game/live/5913858765","moves":"1. e4 c5 2. c3 e6 3. d4 d5 4. e5 a6 5. Nf3 h6 6. Bd3 c4 7. Bc2 b5 8. O-O Nc6 9. Nbd2 Nge7 10. Re1 b4 11. Nf1 a5 12. Ng3 Nf5 13. Nxf5 exf5 14. Ba4 Bd7 15. e6 fxe6 16. Bxc6 Bxc6 17. Ne5 Qb6 18. Qh5+ Ke7 19. Qf7+ Kd6 20. Nxc4+ dxc4 21. Bf4+"},{"id":"5913762381","site":"Chess.com","date":"2020.12.08","white":"wzutali","black":"SenseiDanya","result":"0-1","currentposition":"8/q1r4p/8/qK2k3/6PP/1P6/8/8 w - -","eco":"B35","ecourl":"https://www.chess.com/openings/Sicilian-Defense-Open-Accelerated-Dragon-Modern-Variation...6.Be3-Nf6-7.Bc4-O-O-8.f3","whiteelo":"1869","blackelo":"1774","starttime":"03:50:54","endtime":"03:58:02","link":"https://www.chess.com/game/live/5913762381","moves":"1. e4 c5 2. Nf3 Nc6 3. d4 cxd4 4. Nxd4 g6 5. Nc3 Bg7 6. Be3 Nf6 7. Bc4 O-O 8. f3 Qb6 9. Qd2 Nxe4 10. fxe4 Bxd4 11. Bxd4 Qxd4 12. Qe2 d6 13. Bd3 Be6 14. O-O-O Rac8 15. Kb1 Ne5 16. h3 Rxc3 17. bxc3 Qxc3 18. Qd2 Qa3 19. c4 Bxc4 20. Bxc4 Nxc4 21. Qc2 Ne3 22. Qb3 Qxb3+ 23. axb3 Nxd1 24. Rxd1 Rc8 25. Kb2 Kg7 26. Ra1 a6 27. Ra4 Kf6 28. Rb4 b5 29. Rd4 Ke5 30. Rd2 e6 31. Rf2 f5 32. exf5 gxf5 33. Re2+ Kf6 34. Rf2 e5 35. g4 f4 36. h4 d5 37. Rd2 d4 38. Ka3 f3 39. Kb4 e4 40. Rxd4 f2 41. Rd1 e3 42. Ka5 e2 43. Rd6+ Ke5 44. Rxa6 e1=Q+ 45. Kb6 f1=Q 46. Ra7 Qff2+ 47. Kb7 Rc7+ 48. Ka6 Qxa7+ 49. Kxb5 Qea5#"},{"id":"5913668334","site":"Chess.com","date":"2020.12.08","white":"viethorn","black":"SenseiDanya","result":"0-1","currentposition":"r1b2rk1/p1p3pp/2p5/3p2B1/3Pp1n1/1BP2P2/PP1N2Pq/R2Q1RK1 w - -","eco":"C44","ecourl":"https://www.chess.com/openings/Ponziani-Opening-Ponziani-Countergambit-4.d4","whiteelo":"1725","blackelo":"1763","starttime":"03:30:26","endtime":"03:35:07","link":"https://www.chess.com/game/live/5913668334","moves":"1. e4 e5 2. Nf3 Nc6 3. c3 f5 4. d4 fxe4 5. Nxe5 Nf6 6. Bc4 d5 7. Bb3 Bd6 8. Nxc6 bxc6 9. O-O O-O 10. Bg5 Qe8 11. Nd2 Bxh2+ 12. Kxh2 Ng4+ 13. Kg1 Qh5 14. f3 Qh2#"},{"id":"5913618253","site":"Chess.com","date":"2020.12.08","white":"matthomes","black":"SenseiDanya","result":"0-1","currentposition":"r2qk2r/ppp1pp2/2np2p1/4P2p/2P2PbP/2N2R2/PP4P1/R2QKBb1 w Qkq -","eco":"E70","ecourl":"https://www.chess.com/openings/Kings-Indian-Defense-Normal-Variation-4.e4-d6","whiteelo":"1853","blackelo":"1756","starttime":"03:19:31","endtime":"03:22:22","link":"https://www.chess.com/game/live/5913618253","moves":"1. d4 Nf6 2. c4 g6 3. Nc3 Bg7 4. e4 d6 5. h4 h5 6. Be3 Nc6 7. f4 Ng4 8. Rh3 Nxe3 9. Rxe3 Bxd4 10. Rf3 Bxg1 11. e5 Bg4"},{"id":"5913529555","site":"Chess.com","date":"2020.12.08","white":"SenseiDanya","black":"imvtaj","result":"1-0","currentposition":"7k/n3r1q1/p1p2R2/1pP1P1p1/8/P3P2P/2Q3P1/1B3RK1 b - -","eco":"A41","ecourl":"https://www.chess.com/openings/Queens-Pawn-Opening-1...d6","whiteelo":"1745","blackelo":"1718","starttime":"03:00:08","endtime":"03:08:20","link":"https://www.chess.com/game/live/5913529555","moves":"1. d4 d6 2. Bf4 f5 3. e3 Nf6 4. Nf3 Nbd7 5. Bc4 Nb6 6. Bb3 e6 7. O-O Be7 8. h3 h6 9. c4 O-O 10. Nc3 a6 11. Rc1 Bd7 12. a3 Qe8 13. Ba2 Nc8 14. b4 b5 15. c5 Bc6 16. Bxe6+ Kh8 17. Bxf5 Bxf3 18. Qxf3 Na7 19. Bb1 dxc5 20. bxc5 c6 21. Qe2 g5 22. Be5 Qf7 23. Qc2 Rae8 24. Ne4 Qg7 25. f4 Rf7 26. fxg5 hxg5 27. Nxf6 Bxf6 28. Rxf6 Rxe5 29. dxe5 Re7 30. Rcf1"},{"id":"5913408079","site":"Chess.com","date":"2020.12.08","white":"SenseiDanya","black":"jonathancampos11","result":"1-0","currentposition":"r4r1k/2nBp3/p1P2pq1/P2p4/1p2P2R/3Q3P/1P4P1/2R3K1 b - -","eco":"A43","ecourl":"https://www.chess.com/openings/Old-Benoni-Defense-2.d5","whiteelo":"1737","blackelo":"1753","starttime":"02:34:16","endtime":"02:44:01","link":"https://www.chess.com/game/live/5913408079","moves":"1. d4 c5 2. d5 b5 3. e4 a6 4. a4 b4 5. Bc4 d6 6. Nf3 g6 7. O-O Bg7 8. a5 Nd7 9. c3 Ngf6 10. Re1 O-O 11. Bg5 h6 12. Bh4 g5 13. Bg3 Ne8 14. Qc2 f6 15. Nbd2 Nc7 16. cxb4 cxb4 17. Nd4 Nc5 18. Nc6 Qe8 19. Nb3 Nxb3 20. Bxb3 h5 21. h3 h4 22. Bh2 Nb5 23. Rac1 Bd7 24. Qd3 Bxc6 25. dxc6+ Kh8 26. Be6 Nc7 27. Bd7 Qg6 28. f4 gxf4 29. Bxf4 Bh6 30. Rf1 Bxf4 31. Rxf4 d5 32. Rxh4+"},{"id":"5860778108","site":"Chess.com","date":"2020.12.01","white":"bycb","black":"SenseiDanya","result":"0-1","currentposition":"6k1/1p3ppp/5p2/1b6/8/6P1/1B3PKP/3r4 w - -","eco":"B20","ecourl":"https://www.chess.com/openings/Sicilian-Defense-Wing-Gambit-2...cxb4","whiteelo":"1730","blackelo":"1728","starttime":"10:53:47","endtime":"11:02:34","link":"https://www.chess.com/game/live/5860778108","moves":"1. e4 c5 2. b4 cxb4 3. Bc4 Nf6 4. e5 d5 5. exf6 dxc4 6. Qe2 Be6 7. Bb2 exf6 8. c3 a5 9. Nf3 Nc6 10. O-O Bc5 11. Qe4 O-O 12. cxb4 axb4 13. a3 bxa3 14. Nxa3 Qd3 15. Qxd3 cxd3 16. Nb5 Bb6 17. Nd6 Nb4 18. Ne4 Nc2 19. Rxa8 Rxa8 20. Ne1 Ra2 21. Nxd3 Bc4 22. Nc3 Ra8 23. Ne1 Bxf1 24. Nxc2 Bc4 25. d4 Rd8 26. g3 Bxd4 27. Nxd4 Rxd4 28. Nb5 Rd1+ 29. Kg2 Bxb5"},{"id":"5860757196","site":"Chess.com","date":"2020.12.01","white":"SenseiDanya","black":"Avec1957","result":"1-0","currentposition":"r1b1kb1r/pp3ppp/2n1pq2/2p3B1/3P4/3B1N2/PPP2PPP/R2QK2R b KQkq -","eco":"C10","ecourl":"https://www.chess.com/openings/French-Defense-Rubinstein-Variation-4.Nxe4-Nf6","whiteelo":"1720","blackelo":"1704","starttime":"10:49:29","endtime":"10:52:24","link":"https://www.chess.com/game/live/5860757196","moves":"1. e4 e6 2. d4 d5 3. Nc3 dxe4 4. Nxe4 Nf6 5. Nxf6+ Qxf6 6. Nf3 c5 7. Bd3 Nc6 8. Bg5"},{"id":"5860682705","site":"Chess.com","date":"2020.12.01","white":"SenseiDanya","black":"rakeshtyagi","result":"1-0","currentposition":"4R1k1/8/5KP1/8/1N6/8/PPP5/8 b - -","eco":"B06","ecourl":"https://www.chess.com/openings/Modern-Defense-Standard-Line-3...d6","whiteelo":"1712","blackelo":"1731","starttime":"10:33:47","endtime":"10:42:37","link":"https://www.chess.com/game/live/5860682705","moves":"1. e4 g6 2. d4 Bg7 3. Nc3 d6 4. Be3 Nf6 5. f3 O-O 6. Qd2 Nbd7 7. Bh6 c5 8. d5 a6 9. h4 b5 10. h5 b4 11. Bxg7 Kxg7 12. hxg6 fxg6 13. Qh6+ Kg8 14. Nd1 Rf7 15. Ne3 Rg7 16. Nh3 Qf8 17. Ng5 Ne5 18. O-O-O Nf7 19. Nxf7 Qxf7 20. Bc4 Nh5 21. Rh4 Qf6 22. Rdh1 Bd7 23. f4 Rf8 24. e5 dxe5 25. d6+ e6 26. Ng4 Qxf4+ 27. Qxf4 exf4 28. Ne5 Ng3 29. Nxd7 Nxh1 30. Bxe6+ Kh8 31. Nxf8 Ng3 32. d7 Rxd7 33. Bxd7 Kg7 34. Nxh7 g5 35. Nxg5 Kg6 36. Nh3 Kg7 37. Nxf4 Kf6 38. Kd2 Ke5 39. Rg4 Ne4+ 40. Ke3 Nd6 41. Nd3+ Kd5 42. Rg5+ Nf5+ 43. Rxf5+ Kd6 44. Rxc5 Kxd7 45. Nxb4 a5 46. Rxa5 Kc7 47. g4 Kd7 48. Rd5+ Ke7 49. g5 Kf7 50. Kf4 Kg6 51. Rd6+ Kf7 52. Kf5 Ke7 53. Re6+ Kf7 54. g6+ Kg7 55. Re7+ Kf8 56. Kf6 Kg8 57. Re8#"},{"id":"5860591675","site":"Chess.com","date":"2020.12.01","white":"SenseiDanya","black":"latorre22","result":"1-0","currentposition":"2r1r1k1/p5p1/1p2R1pq/3p2N1/3PnPQ1/2P5/PP4P1/4R1K1 b - -","eco":"B13","ecourl":"https://www.chess.com/openings/Caro-Kann-Defense-Exchange-Variation...4.Bd3-Nc6-5.c3-Nf6","whiteelo":"1703","blackelo":"1839","starttime":"10:14:06","endtime":"10:23:37","link":"https://www.chess.com/game/live/5860591675","moves":"1. e4 c6 2. d4 d5 3. exd5 cxd5 4. Bd3 Nc6 5. c3 Nf6 6. Ne2 Bg4 7. Qb3 Qd7 8. O-O e6 9. Bf4 Be7 10. Nd2 O-O 11. h3 Bh5 12. Ng3 Bg6 13. Bxg6 hxg6 14. Nf3 b6 15. Rfe1 Na5 16. Qc2 Nc4 17. h4 Rac8 18. Ng5 Bd6 19. Bxd6 Qxd6 20. h5 Qf4 21. Nh3 Qh6 22. hxg6 fxg6 23. Rxe6 Rfe8 24. Rae1 Kf7 25. Qe2 Nd6 26. f4 Nde4 27. Nxe4 Nxe4 28. Ng5+ Kg8 29. Qg4"},{"id":"5860530934","site":"Chess.com","date":"2020.12.01","white":"mbidar","black":"SenseiDanya","result":"0-1","currentposition":"1r4k1/7p/3pp3/2p2p2/3n1P2/3PK1P1/1r5P/R4B2 w - -","eco":"B20","ecourl":"https://www.chess.com/openings/Sicilian-Defense-Staunton-Cochrane-Variation","whiteelo":"1695","blackelo":"1692","starttime":"10:00:50","endtime":"10:07:44","link":"https://www.chess.com/game/live/5860530934","moves":"1. e4 c5 2. c4 Nc6 3. Nc3 g6 4. Nf3 Bg7 5. d3 d6 6. Be3 Bg4 7. Be2 Bxf3 8. Bxf3 e6 9. Rc1 Nge7 10. O-O O-O 11. b3 Nd4 12. Bg4 Nec6 13. f4 f5 14. Bh3 Qa5 15. Qd2 a6 16. a4 Nxb3 17. Qc2 Nxc1 18. Qxc1 Qxc3 19. Qxc3 Bxc3 20. exf5 gxf5 21. Rb1 Rab8 22. g3 Bd4 23. Kf2 Bxe3+ 24. Kxe3 Nd4 25. Bg2 b5 26. axb5 axb5 27. cxb5 Rxb5 28. Ra1 Rb2 29. Bf1 Rfb8"},{"id":"5860481431","site":"Chess.com","date":"2020.12.01","white":"SenseiDanya","black":"raoufsaad_52","result":"1-0","currentposition":"rnbq1r2/p4pp1/1pp1pb2/6Nk/3P2PP/2PQ4/PP3P2/R1B1K2R b KQ g3","eco":"C00","ecourl":"https://www.chess.com/openings/French-Defense-Normal-Variation","whiteelo":"1684","blackelo":"1701","starttime":"09:49:43","endtime":"09:53:30","link":"https://www.chess.com/game/live/5860481431","moves":"1. e4 e6 2. d4 c6 3. Nc3 d5 4. Nf3 dxe4 5. Nxe4 Be7 6. Bd3 Nf6 7. Nxf6+ Bxf6 8. c3 O-O 9. h4 b6 10. Bxh7+ Kxh7 11. Ng5+ Kg6 12. Qd3+ Kh5 13. g4+"},{"id":"5860442631","site":"Chess.com","date":"2020.12.01","white":"SenseiDanya","black":"felixbernas","result":"1-0","currentposition":"8/p7/6pp/2p5/2Pk1B2/1P2Q3/P4PPP/2K5 b - -","eco":"B01","ecourl":"https://www.chess.com/openings/Scandinavian-Defense-Mieses-Kotrc-Main-Line-4.d4","whiteelo":"1675","blackelo":"1664","starttime":"09:40:53","endtime":"09:47:36","link":"https://www.chess.com/game/live/5860442631","moves":"1. e4 d5 2. exd5 Qxd5 3. Nc3 Qa5 4. d4 Bf5 5. Nf3 Nc6 6. Bb5 Bd7 7. d5 Nb8 8. Bc4 Qc5 9. Qe2 Nf6 10. Be3 Qb4 11. O-O-O Na6 12. Ne5 O-O-O 13. Bxa6 bxa6 14. Nxf7 Rg8 15. Qxa6+ Qb7 16. Qxb7+ Kxb7 17. Nxd8+ Kc8 18. Ne6 Bxe6 19. dxe6 g6 20. Rd4 Ne8 21. Rd7 Nd6 22. Nd5 c6 23. Nxe7+ Bxe7 24. Rxe7 Re8 25. Rxe8+ Nxe8 26. Rd1 Kc7 27. e7 Nd6 28. Rxd6 Kxd6 29. e8=Q c5 30. Bf4+ Kd5 31. b3 h6 32. c4+ Kd4 33. Qe3#"}]